ALU/src/ALU.sv
//try after to implement at logic level. Or pipelined
module ALU (
    input logic [3:0] sel,
    input logic [3:0] A,
    input logic [3:0] B,
    input logic M,
    input logic Cn,
    output logic [3:0] F,
    output logic ABFlag
);

    logic [3:0] Fin1, Fin2;
    always_comb begin
        if(M) begin
            case(sel)
                4'd0:Fin1 = ~A;
                4'd1:Fin1 = ~(A+B);
                4'd2:Fin1 = ~A & B;
                4'd3:Fin1 = 4'd0;
                4'd4:Fin1 = ~(A&B);
                4'd5:Fin1 = ~B;
                4'd6:Fin1 = A ^ B;
                4'd7:Fin1 = A & ~B;
                4'd8:Fin1 = ~A + B;
                4'd9:Fin1 = ~(A ^ B);
                4'd10:Fin1 = B;
                4'd11:Fin1 = A & B;
                4'd12:Fin1 = 4'd15;
                4'd13:Fin1 = (A + ~B);
                4'd14:Fin1 = A + B;
                4'd15:Fin1 = A;
            endcase
        end
        else begin
                case(sel)
                    4'd0:Fin2 = A;
                    4'd1:Fin2 = (A+B);
                    4'd2:Fin2 = A + ~B;
                    4'd3:Fin2 = 4'd15;
                    4'd4:Fin2 = A + (~A|B);
                    4'd5:Fin2 = (A+B) + (~A|B);
                    4'd6:Fin2 = (A-B)-1;
                    4'd7:Fin2 = (A&~B)-1;
                    4'd8:Fin2 = A + (A&B);
                    4'd9:Fin2 = (A + B);
                    4'd10:Fin2 = (A+ ~B) + (A&B);
                    4'd11:Fin2 = (A&B)-1;
                    4'd12:Fin2 = A + (A<<1);
                    4'd13:Fin2 = (A+B) + A;
                    4'd14:Fin2 = (A + ~B) + A;
                    4'd15:Fin2 = A-1;
                endcase
                if(Cn) Fin1 = Fin2;
                else Fin1 = Fin2 + 1;
            end
        end
        assign F = Fin1;
        assign ABFlag = (Fin1[0] & Fin1[1] & Fin1[2] & Fin1[3]);
endmodule

MUX/src/mux.sv
module mux (
    input logic sel,
    input logic [3:0] programP,
    input logic [3:0] Ram,
    input logic enable,
    output logic [3:0] outBits
);

always_comb begin
    if(enable) begin
        if(sel)
            outBits = Ram;
        else
            outBits = programP;
    end
    else outBits = 4'd0;
end


endmodule

RAM/RAM.sv
`timescale 1ns/1ps
module RAM
    (
        input logic write_en,
        input logic CS,
        input logic [3:0] addr,
        input logic [3:0] dataIN,
        output logic [3:0] dataOut
    );

    logic [3:0] dataCells [15:0];


    initial begin
    integer i;
        for (i = 0; i <= 15; i = i + 1) begin
            dataCells[i] = 4'd0;
        end
    end


    always_comb begin
        if(CS) begin
            if(~(write_en)) begin
                dataOut = 4'd0;
            end
            else begin
                dataOut = dataCells[addr];
            end
        end
    end

    always_latch begin
        if (CS && ~write_en) begin
            dataCells[addr] = dataIN;
        end
    end

endmodule

FF/src/FF.sv
`timescale 1ns/1ps
module FF (
    input logic clk,
    input logic en,
    input logic [3:0] dIn,
    output logic [3:0] dOut
);
always_ff @(posedge clk) begin
    if(!en)
        dOut <= dIn;
    else
        dOut <= dOut;
end

endmodule

ControlROM/src/ControlROM.sv
module ControlROM (
    input logic [3:0] addr,
    output logic [9:0] prog
);


logic [7:0] progInt;

always_comb begin : progBlock
    case(addr)
        4'd0: progInt = 8'b10101010;
        4'd1: progInt = 8'b10101010;
        4'd2: progInt = 8'b10010010;
        4'd3: progInt = 8'b10010010;
        4'd4: progInt = 8'b01100010;
        4'd5: progInt = 8'b01100010;
        4'd6: progInt = 8'b10101100;
        4'd7: progInt = 8'b10101100;
        4'd8: progInt = 8'b10101110;
        4'd9: progInt = 8'b10101110;
        // 4'd10: do something with I/O pins
        // 4'd11:
        4'd12: progInt = 8'b00001111;
        4'd13: progInt = 8'b00001111;
        4'd14: progInt = 8'b11001111;
        4'd15: progInt = 8'b11001111;
        default: progInt = 8'd0;
    endcase
end 
assign prog[7:0] = progInt;
assign prog[8] = progInt[4];
assign prog[9] = addr[0];
endmodule

ProgramROM/ProgramROM.sv
`timescale 1ns/1ps
module ProgramROM (
    input logic [3:0] addr,
    output logic [7:0] prog
);

always_comb begin : progBlock
    case(addr)
        4'd0:prog = 8'h82;
        4'd1:prog = 8'h10;
        4'd2:prog = 8'h21;
        4'd3:prog = 8'h62;
        4'd4:prog = 8'hC0;
        default: prog = 8'h00;
    endcase
end 
endmodule

ProgramCounter/PC.sv
`timescale 1ns/1ps
module PC(
    input logic clk,
    input logic progC,
    input logic [3:0] progP,
    input logic ABFlag,
    output logic [3:0] programCount,
    output logic cp
);

logic [3:0]counter = 0;
logic [3:0] programCountint = 0;

always_ff @(posedge clk) begin : blockName
    if(progC && ABFlag) begin
        programCountint <= progP;
        counter <= 0;
    end else begin
        if(counter == 4'hF)
            counter <= 0;
        else
            counter <= counter + 1;
    end
end
always_ff @(posedge counter[3]) begin
        if(programCountint<15) 
            programCountint <= programCountint + 1;
        else
            programCountint <= 0;
        end


assign cp = counter[3];
assign programCount = programCountint;


endmodule

TopLevel/src/TopLevel.sv
`include "ALU/src/ALU.sv"
`include "ControlROM/src/ControlROM.sv"
`include "ProgramCounter/src/PC.sv"
`include "RAM/src/RAM.sv"
`include "MUX/src/mux.sv"
`include "ProgramROM/src/ProgramROM.sv"
`include "FF/src/FF.sv"

module TopLevel(
    input logic clk,
    output logic [3:0] Acc,
    output logic [3:0] programCountOut,
    output logic [7:0] progPOut,
    output logic [9:0] progCOut,
    output logic [3:0] muxOutOut,
    output logic [3:0] addrOutOut,
    output logic [3:0] ramOutOut,
    output logic [3:0] AluOutOut,
    output logic cpOut,
    output logic ABFlagOut,
    output logic PCc0,
    output logic RWc1,
    output logic Accc2,
    output logic Mc3,
    output logic Cnc8,
    output logic S0c4,
    output logic S1c5,
    output logic S2c6,
    output logic S3c7,
    output logic Selc9
);

logic [3:0] programCount;
logic cp;
logic ABFlag;
logic [7:0] progP;
logic [9:0] progC;
logic [3:0] muxOut;
logic [3:0] addrOut;
logic [3:0] ramOut;
logic [3:0] AccOut;
logic [3:0] AluOut;

PC Pcblock(.clk(clk), .programCount(programCount), .cp(cp), .ABFlag(ABFlag), .progC(progC[0]), .progP(progP[3:0]));

ProgramROM programBlock (.prog(progP), .addr(programCount));

ControlROM controlBlock (.addr(progP[7:4]), .prog(progC));

FF addrBlock(.clk(cp), .en(1'd0), .dIn(muxOut), .dOut(addrOut));

FF AccBlock(.clk(cp), .en(progC[2]), .dIn(AluOut), .dOut(AccOut));

RAM ramBlock(.write_en(progC[1]), .CS(1'd1), .addr(addrOut), .dataOut(ramOut), .dataIN(AccOut));

mux muxblock (.programP(progP[3:0]), .sel(progC[9]), .Ram(ramOut), .enable(1'd1), .outBits(muxOut));

ALU aluBlock (.sel(progC[7:4]), .A(AccOut), .B(muxOut), .M(progC[3]), .Cn(progC[8]), .F(AluOut), .ABFlag(ABFlag));

assign Acc = AccOut;
assign ramOutOut = ramOut;
assign programCountOut = programCount;
assign AluOutOut = AluOut;
assign progPOut = progP;
assign muxOutOut = muxOut;
assign addrOutOut = addrOut;
assign cpOut = cp;
assign ABFlagOut = ABFlag;
assign progCOut = progC;
assign PCc0 = progC[0];
assign RWc1 = progC[1];
assign Accc2 = progC[2];
assign Mc3 = progC[3];
assign S0c4 = progC[4];
assign S1c5 = progC[5];
assign S2c6 = progC[6];
assign S3c7 = progC[7];
assign Cnc8 = progC[8];
assign Selc9 = progC[9];




endmodule

TopLevel/testB/TopLeveltestB.sv
`timescale 1ns/1ps
module TopLevelTestB;

    logic clk;
    logic ABFlagOut;
    logic cpOut;
    logic [3:0] Acc;
    logic [3:0] programCountOut;
    logic [3:0] AluOutOut;
    logic [9:0] progCOut;
    logic [7:0] progPOut;
    logic [3:0] ramOutOut;
    logic [3:0] addrOutOut;
    logic [3:0] muxOutOut;
    logic PCc0;
    logic RWc1;
    logic Accc2;
    logic Mc3;
    logic S0c4;
    logic S1c5;
    logic S2c6;
    logic S3c7;
    logic Cnc8;
    logic Selc9;

    TopLevel uut (.clk(clk), .Acc(Acc), .programCountOut(programCountOut), .AluOutOut(AluOutOut), 
    .progCOut(progCOut), .progPOut(progPOut), .muxOutOut(muxOutOut), .ramOutOut(ramOutOut), .addrOutOut(addrOutOut),
    .cpOut(cpOut), .ABFlagOut(ABFlagOut),
    .PCc0(PCc0),
    .RWc1(RWc1),
    .Accc2(Accc2),
    .Mc3(Mc3),
    .S0c4(S0c4),
    .S1c5(S1c5),
    .S2c6(S2c6),
    .S3c7(S3c7),
    .Cnc8(Cnc8),
    .Selc9(Selc9)
    );

    initial begin
        clk = 0;
        forever #5 clk = ~clk;
    end



    initial begin
        $dumpfile("curTest.vcd");
        $dumpvars(0,TopLevelTestB);
        #10000
        $finish;
    end
endmodule

curTest.vcd
$date
	Thu Mar  5 01:37:58 2026
$end
$version
	Icarus Verilog
$end
$timescale
	1ps
$end
$scope module TopLevelTestB $end
$var wire 4 ! programCountOut [3:0] $end
$var wire 8 " progPOut [7:0] $end
$var wire 4 # AluOutOut [3:0] $end
$var wire 4 $ Acc [3:0] $end
$var reg 1 % clk $end
$scope module uut $end
$var wire 4 & Acc [3:0] $end
$var wire 4 ' AluOutOut [3:0] $end
$var wire 1 % clk $end
$var wire 8 ( progPOut [7:0] $end
$var wire 4 ) programCountOut [3:0] $end
$var wire 4 * ramOut [3:0] $end
$var wire 4 + programCount [3:0] $end
$var wire 8 , progP [7:0] $end
$var wire 10 - progC [9:0] $end
$var wire 4 . muxOut [3:0] $end
$var wire 1 / cp $end
$var wire 4 0 addrOut [3:0] $end
$var wire 4 1 AluOut [3:0] $end
$var wire 4 2 AccOut [3:0] $end
$var wire 1 3 ABFlag $end
$scope module AccBlock $end
$var wire 1 4 en $end
$var wire 4 5 dIn [3:0] $end
$var wire 1 / clk $end
$var reg 4 6 dOut [3:0] $end
$upscope $end
$scope module Pcblock $end
$var wire 1 % clk $end
$var wire 1 7 progC $end
$var wire 4 8 progP [3:0] $end
$var wire 4 9 programCount [3:0] $end
$var wire 1 / cp $end
$var wire 1 3 ABFlag $end
$var reg 4 : counter [3:0] $end
$var reg 4 ; programCountint [3:0] $end
$scope begin blockName $end
$upscope $end
$upscope $end
$scope module addrBlock $end
$var wire 1 / clk $end
$var wire 1 < en $end
$var wire 4 = dIn [3:0] $end
$var reg 4 > dOut [3:0] $end
$upscope $end
$scope module aluBlock $end
$var wire 4 ? A [3:0] $end
$var wire 1 3 ABFlag $end
$var wire 1 @ Cn $end
$var wire 4 A F [3:0] $end
$var wire 1 B M $end
$var wire 4 C sel [3:0] $end
$var wire 4 D B [3:0] $end
$var reg 4 E Fin1 [3:0] $end
$var reg 4 F Fin2 [3:0] $end
$upscope $end
$scope module controlBlock $end
$var wire 4 G addr [3:0] $end
$var wire 10 H prog [9:0] $end
$var reg 8 I progInt [7:0] $end
$scope begin progBlock $end
$upscope $end
$upscope $end
$scope module muxblock $end
$var wire 1 J enable $end
$var wire 4 K programP [3:0] $end
$var wire 1 L sel $end
$var wire 4 M Ram [3:0] $end
$var reg 4 N outBits [3:0] $end
$upscope $end
$scope module programBlock $end
$var wire 4 O addr [3:0] $end
$var reg 8 P prog [7:0] $end
$scope begin progBlock $end
$upscope $end
$upscope $end
$scope module ramBlock $end
$var wire 1 Q CS $end
$var wire 4 R addr [3:0] $end
$var wire 4 S dataIN [3:0] $end
$var wire 1 T write_en $end
$var reg 4 U dataOut [3:0] $end
$scope begin $unm_blk_7 $end
$var integer 32 V i [31:0] $end
$upscope $end
$upscope $end
$upscope $end
$upscope $end
$enddefinitions $end
$comment Show the parameter values. $end
$dumpall
$end
#0
$dumpvars
b10000 V
bx U
1T
bx S
bx R
1Q
b10000010 P
b0 O
b10 N
bx M
0L
b10 K
1J
b10101110 I
b10101110 H
b1000 G
b0 F
b10 E
b10 D
b1010 C
1B
b10 A
0@
bx ?
bx >
b10 =
0<
b0 ;
b0 :
b0 9
b10 8
07
bx 6
b10 5
14
03
bx 2
b10 1
bx 0
0/
b10 .
b10101110 -
b10000010 ,
b0 +
bx *
b0 )
b10000010 (
b10 '
bx &
0%
bx $
b10 #
b10000010 "
b0 !
$end
#5000
b1 :
1%
#10000
0%
#15000
b10 :
1%
#20000
0%
#25000
b11 :
1%
#30000
0%
#35000
b100 :
1%
#40000
0%
#45000
b101 :
1%
#50000
0%
#55000
b110 :
1%
#60000
0%
#65000
b111 :
1%
#70000
0%
#75000
04
1L
b0 #
b0 '
b0 1
b0 5
b0 A
b0 E
b10101010 I
b1010101010 -
b1010101010 H
b0 .
b0 =
b0 D
b0 N
b0 K
b1 G
b0 8
b0 *
b0 M
b0 U
b10000 "
b10000 (
b10000 ,
b10000 P
b10 0
b10 >
b10 R
b1 !
b1 )
b1 +
b1 9
b1 ;
b1 O
1/
b1000 :
1%
#80000
0%
#85000
b1001 :
1%
#90000
0%
#95000
b1010 :
1%
#100000
0%
#105000
b1011 :
1%
#110000
0%
#115000
b1100 :
1%
#120000
0%
#125000
b1101 :
1%
#130000
0%
#135000
b1110 :
1%
#140000
0%
#145000
b1111 :
1%
#150000
0%
#155000
0/
b0 :
1%
#160000
0%
#165000
b1 :
1%
#170000
0%
#175000
b10 :
1%
#180000
0%
#185000
b11 :
1%
#190000
0%
#195000
b100 :
1%
#200000
0%
#205000
b101 :
1%
#210000
0%
#215000
b110 :
1%
#220000
0%
#225000
b111 :
1%
#230000
0%
#235000
1@
b1 #
b1 '
b1 1
b1 5
b1 A
b1 E
b1 F
b1 .
b1 =
b1 D
b1 N
0B
b1001 C
0L
b10010010 I
b110010010 -
b110010010 H
b1 K
b10 G
b1 8
b100001 "
b100001 (
b100001 ,
b100001 P
b0 $
b0 &
b0 2
b0 6
b0 ?
b0 S
b0 0
b0 >
b0 R
b10 !
b10 )
b10 +
b10 9
b10 ;
b10 O
1/
b1000 :
1%
#240000
0%
#245000
b1001 :
1%
#250000
0%
#255000
b1010 :
1%
#260000
0%
#265000
b1011 :
1%
#270000
0%
#275000
b1100 :
1%
#280000
0%
#285000
b1101 :
1%
#290000
0%
#295000
b1110 :
1%
#300000
0%
#305000
b1111 :
1%
#310000
0%
#315000
0/
b0 :
1%
#320000
0%
#325000
b1 :
1%
#330000
0%
#335000
b10 :
1%
#340000
0%
#345000
b11 :
1%
#350000
0%
#355000
b100 :
1%
#360000
0%
#365000
b101 :
1%
#370000
0%
#375000
b110 :
1%
#380000
0%
#385000
b111 :
1%
#390000
0%
#395000
0@
1B
b1010 C
0T
14
b10 .
b10 =
b10 D
b10 N
b10101100 -
b10101100 H
b10101100 I
b10 K
b110 G
b10 8
b0 F
b10 #
b10 '
b10 1
b10 5
b10 A
b10 E
b1100010 "
b1100010 (
b1100010 ,
b1100010 P
b1 0
b1 >
b1 R
b1 $
b1 &
b1 2
b1 6
b1 ?
b1 S
b11 !
b11 )
b11 +
b11 9
b11 ;
b11 O
1/
b1000 :
1%
#400000
0%
#405000
b1001 :
1%
#410000
0%
#415000
b1010 :
1%
#420000
0%
#425000
b1011 :
1%
#430000
0%
#435000
b1100 :
1%
#440000
0%
#445000
b1101 :
1%
#450000
0%
#455000
b1110 :
1%
#460000
0%
#465000
b1111 :
1%
#470000
0%
#475000
0/
b0 :
1%
#480000
0%
#485000
b1 :
1%
#490000
0%
#495000
b10 :
1%
#500000
0%
#505000
b11 :
1%
#510000
0%
#515000
b100 :
1%
#520000
0%
#525000
b101 :
1%
#530000
0%
#535000
b110 :
1%
#540000
0%
#545000
b111 :
1%
#550000
0%
#555000
13
1@
b1 *
b1 M
b1 U
b1111 #
b1111 '
b1111 1
b1111 5
b1111 A
b1111 E
b101 C
1T
17
b0 .
b0 =
b0 D
b0 N
b101011111 -
b101011111 H
b1011111 I
b0 K
b1100 G
b0 8
b11000000 "
b11000000 (
b11000000 ,
b11000000 P
b10 0
b10 >
b10 R
b100 !
b100 )
b100 +
b100 9
b100 ;
b100 O
1/
b1000 :
1%
#560000
0%
#565000
03
0@
b10 #
b10 '
b10 1
b10 5
b10 A
b10 E
b1010 C
07
b10 .
b10 =
b10 D
b10 N
b10101110 -
b10101110 H
b10101110 I
b10 K
b1000 G
b10 8
0/
b10000010 "
b10000010 (
b10000010 ,
b10000010 P
b0 :
b0 !
b0 )
b0 +
b0 9
b0 ;
b0 O
1%
#570000
0%
#575000
b1 :
1%
#580000
0%
#585000
b10 :
1%
#590000
0%
#595000
b11 :
1%
#600000
0%
#605000
b100 :
1%
#610000
0%
#615000
b101 :
1%
#620000
0%
#625000
b110 :
1%
#630000
0%
#635000
b111 :
1%
#640000
0%
#645000
b1 #
b1 '
b1 1
b1 5
b1 A
b1 E
04
1L
b1 .
b1 =
b1 D
b1 N
b10101010 I
b1010101010 -
b1010101010 H
b0 K
b1 G
b0 8
b10000 "
b10000 (
b10000 ,
b10000 P
b1 !
b1 )
b1 +
b1 9
b1 ;
b1 O
1/
b1000 :
1%
#650000
0%
#655000
b1001 :
1%
#660000
0%
#665000
b1010 :
1%
#670000
0%
#675000
b1011 :
1%
#680000
0%
#685000
b1100 :
1%
#690000
0%
#695000
b1101 :
1%
#700000
0%
#705000
b1110 :
1%
#710000
0%
#715000
b1111 :
1%
#720000
0%
#725000
0/
b0 :
1%
#730000
0%
#735000
b1 :
1%
#740000
0%
#745000
b10 :
1%
#750000
0%
#755000
b11 :
1%
#760000
0%
#765000
b100 :
1%
#770000
0%
#775000
b101 :
1%
#780000
0%
#785000
b110 :
1%
#790000
0%
#795000
b111 :
1%
#800000
0%
#805000
1@
b10 F
b10 #
b10 '
b10 1
b10 5
b10 A
b10 E
0B
b1001 C
0L
b10010010 I
b110010010 -
b110010010 H
b1 K
b10 G
b1 8
b100001 "
b100001 (
b100001 ,
b100001 P
b1 0
b1 >
b1 R
b10 !
b10 )
b10 +
b10 9
b10 ;
b10 O
1/
b1000 :
1%
#810000
0%
#815000
b1001 :
1%
#820000
0%
#825000
b1010 :
1%
#830000
0%
#835000
b1011 :
1%
#840000
0%
#845000
b1100 :
1%
#850000
0%
#855000
b1101 :
1%
#860000
0%
#865000
b1110 :
1%
#870000
0%
#875000
b1111 :
1%
#880000
0%
#885000
0/
b0 :
1%
#890000
0%
#895000
b1 :
1%
#900000
0%
#905000
b10 :
1%
#910000
0%
#915000
b11 :
1%
#920000
0%
#925000
b100 :
1%
#930000
0%
#935000
b101 :
1%
#940000
0%
#945000
b110 :
1%
#950000
0%
#955000
b111 :
1%
#960000
0%
#965000
0@
b0 *
b0 M
b0 U
1B
b1010 C
0T
14
b10 .
b10 =
b10 D
b10 N
b10101100 -
b10101100 H
b10101100 I
b10 K
b110 G
b10 8
b0 F
b10 #
b10 '
b10 1
b10 5
b10 A
b10 E
b1100010 "
b1100010 (
b1100010 ,
b1100010 P
b10 $
b10 &
b10 2
b10 6
b10 ?
b10 S
b11 !
b11 )
b11 +
b11 9
b11 ;
b11 O
1/
b1000 :
1%
#970000
0%
#975000
b1001 :
1%
#980000
0%
#985000
b1010 :
1%
#990000
0%
#995000
b1011 :
1%
#1000000
0%
#1005000
b1100 :
1%
#1010000
0%
#1015000
b1101 :
1%
#1020000
0%
#1025000
b1110 :
1%
#1030000
0%
#1035000
b1111 :
1%
#1040000
0%
#1045000
0/
b0 :
1%
#1050000
0%
#1055000
b1 :
1%
#1060000
0%
#1065000
b10 :
1%
#1070000
0%
#1075000
b11 :
1%
#1080000
0%
#1085000
b100 :
1%
#1090000
0%
#1095000
b101 :
1%
#1100000
0%
#1105000
b110 :
1%
#1110000
0%
#1115000
b111 :
1%
#1120000
0%
#1125000
13
1@
b10 *
b10 M
b10 U
b1111 #
b1111 '
b1111 1
b1111 5
b1111 A
b1111 E
b101 C
1T
17
b0 .
b0 =
b0 D
b0 N
b101011111 -
b101011111 H
b1011111 I
b0 K
b1100 G
b0 8
b11000000 "
b11000000 (
b11000000 ,
b11000000 P
b10 0
b10 >
b10 R
b100 !
b100 )
b100 +
b100 9
b100 ;
b100 O
1/
b1000 :
1%
#1130000
0%
#1135000
03
0@
b10 #
b10 '
b10 1
b10 5
b10 A
b10 E
b1010 C
07
b10 .
b10 =
b10 D
b10 N
b10101110 -
b10101110 H
b10101110 I
b10 K
b1000 G
b10 8
0/
b10000010 "
b10000010 (
b10000010 ,
b10000010 P
b0 :
b0 !
b0 )
b0 +
b0 9
b0 ;
b0 O
1%
#1140000
0%
#1145000
b1 :
1%
#1150000
0%
#1155000
b10 :
1%
#1160000
0%
#1165000
b11 :
1%
#1170000
0%
#1175000
b100 :
1%
#1180000
0%
#1185000
b101 :
1%
#1190000
0%
#1195000
b110 :
1%
#1200000
0%
#1205000
b111 :
1%
#1210000
0%
#1215000
b10 #
b10 '
b10 1
b10 5
b10 A
b10 E
04
1L
b10 .
b10 =
b10 D
b10 N
b10101010 I
b1010101010 -
b1010101010 H
b0 K
b1 G
b0 8
b10000 "
b10000 (
b10000 ,
b10000 P
b1 !
b1 )
b1 +
b1 9
b1 ;
b1 O
1/
b1000 :
1%
#1220000
0%
#1225000
b1001 :
1%
#1230000
0%
#1235000
b1010 :
1%
#1240000
0%
#1245000
b1011 :
1%
#1250000
0%
#1255000
b1100 :
1%
#1260000
0%
#1265000
b1101 :
1%
#1270000
0%
#1275000
b1110 :
1%
#1280000
0%
#1285000
b1111 :
1%
#1290000
0%
#1295000
0/
b0 :
1%
#1300000
0%
#1305000
b1 :
1%
#1310000
0%
#1315000
b10 :
1%
#1320000
0%
#1325000
b11 :
1%
#1330000
0%
#1335000
b100 :
1%
#1340000
0%
#1345000
b101 :
1%
#1350000
0%
#1355000
b110 :
1%
#1360000
0%
#1365000
b111 :
1%
#1370000
0%
#1375000
1@
b11 F
b11 #
b11 '
b11 1
b11 5
b11 A
b11 E
b1 .
b1 =
b1 D
b1 N
0B
b1001 C
0L
b10010010 I
b110010010 -
b110010010 H
b1 K
b10 G
b1 8
b100001 "
b100001 (
b100001 ,
b100001 P
b10 !
b10 )
b10 +
b10 9
b10 ;
b10 O
1/
b1000 :
1%
#1380000
0%
#1385000
b1001 :
1%
#1390000
0%
#1395000
b1010 :
1%
#1400000
0%
#1405000
b1011 :
1%
#1410000
0%
#1415000
b1100 :
1%
#1420000
0%
#1425000
b1101 :
1%
#1430000
0%
#1435000
b1110 :
1%
#1440000
0%
#1445000
b1111 :
1%
#1450000
0%
#1455000
0/
b0 :
1%
#1460000
0%
#1465000
b1 :
1%
#1470000
0%
#1475000
b10 :
1%
#1480000
0%
#1485000
b11 :
1%
#1490000
0%
#1495000
b100 :
1%
#1500000
0%
#1505000
b101 :
1%
#1510000
0%
#1515000
b110 :
1%
#1520000
0%
#1525000
b111 :
1%
#1530000
0%
#1535000
0@
b0 *
b0 M
b0 U
1B
b1010 C
0T
14
b10 .
b10 =
b10 D
b10 N
b10101100 -
b10101100 H
b10101100 I
b10 K
b110 G
b10 8
b0 F
b10 #
b10 '
b10 1
b10 5
b10 A
b10 E
b1100010 "
b1100010 (
b1100010 ,
b1100010 P
b1 0
b1 >
b1 R
b11 $
b11 &
b11 2
b11 6
b11 ?
b11 S
b11 !
b11 )
b11 +
b11 9
b11 ;
b11 O
1/
b1000 :
1%
#1540000
0%
#1545000
b1001 :
1%
#1550000
0%
#1555000
b1010 :
1%
#1560000
0%
#1565000
b1011 :
1%
#1570000
0%
#1575000
b1100 :
1%
#1580000
0%
#1585000
b1101 :
1%
#1590000
0%
#1595000
b1110 :
1%
#1600000
0%
#1605000
b1111 :
1%
#1610000
0%
#1615000
0/
b0 :
1%
#1620000
0%
#1625000
b1 :
1%
#1630000
0%
#1635000
b10 :
1%
#1640000
0%
#1645000
b11 :
1%
#1650000
0%
#1655000
b100 :
1%
#1660000
0%
#1665000
b101 :
1%
#1670000
0%
#1675000
b110 :
1%
#1680000
0%
#1685000
b111 :
1%
#1690000
0%
#1695000
13
1@
b11 *
b11 M
b11 U
b1111 #
b1111 '
b1111 1
b1111 5
b1111 A
b1111 E
b101 C
1T
17
b0 .
b0 =
b0 D
b0 N
b101011111 -
b101011111 H
b1011111 I
b0 K
b1100 G
b0 8
b11000000 "
b11000000 (
b11000000 ,
b11000000 P
b10 0
b10 >
b10 R
b100 !
b100 )
b100 +
b100 9
b100 ;
b100 O
1/
b1000 :
1%
#1700000
0%
#1705000
03
0@
b10 #
b10 '
b10 1
b10 5
b10 A
b10 E
b1010 C
07
b10 .
b10 =
b10 D
b10 N
b10101110 -
b10101110 H
b10101110 I
b10 K
b1000 G
b10 8
0/
b10000010 "
b10000010 (
b10000010 ,
b10000010 P
b0 :
b0 !
b0 )
b0 +
b0 9
b0 ;
b0 O
1%
#1710000
0%
#1715000
b1 :
1%
#1720000
0%
#1725000
b10 :
1%
#1730000
0%
#1735000
b11 :
1%
#1740000
0%
#1745000
b100 :
1%
#1750000
0%
#1755000
b101 :
1%
#1760000
0%
#1765000
b110 :
1%
#1770000
0%
#1775000
b111 :
1%
#1780000
0%
#1785000
b11 #
b11 '
b11 1
b11 5
b11 A
b11 E
04
1L
b11 .
b11 =
b11 D
b11 N
b10101010 I
b1010101010 -
b1010101010 H
b0 K
b1 G
b0 8
b10000 "
b10000 (
b10000 ,
b10000 P
b1 !
b1 )
b1 +
b1 9
b1 ;
b1 O
1/
b1000 :
1%
#1790000
0%
#1795000
b1001 :
1%
#1800000
0%
#1805000
b1010 :
1%
#1810000
0%
#1815000
b1011 :
1%
#1820000
0%
#1825000
b1100 :
1%
#1830000
0%
#1835000
b1101 :
1%
#1840000
0%
#1845000
b1110 :
1%
#1850000
0%
#1855000
b1111 :
1%
#1860000
0%
#1865000
0/
b0 :
1%
#1870000
0%
#1875000
b1 :
1%
#1880000
0%
#1885000
b10 :
1%
#1890000
0%
#1895000
b11 :
1%
#1900000
0%
#1905000
b100 :
1%
#1910000
0%
#1915000
b101 :
1%
#1920000
0%
#1925000
b110 :
1%
#1930000
0%
#1935000
b111 :
1%
#1940000
0%
#1945000
1@
b100 F
0B
b1001 C
0L
b100 #
b100 '
b100 1
b100 5
b100 A
b100 E
b10010010 I
b110010010 -
b110010010 H
b1 .
b1 =
b1 D
b1 N
b1 K
b10 G
b1 8
b0 *
b0 M
b0 U
b100001 "
b100001 (
b100001 ,
b100001 P
b11 0
b11 >
b11 R
b10 !
b10 )
b10 +
b10 9
b10 ;
b10 O
1/
b1000 :
1%
#1950000
0%
#1955000
b1001 :
1%
#1960000
0%
#1965000
b1010 :
1%
#1970000
0%
#1975000
b1011 :
1%
#1980000
0%
#1985000
b1100 :
1%
#1990000
0%
#1995000
b1101 :
1%
#2000000
0%
#2005000
b1110 :
1%
#2010000
0%
#2015000
b1111 :
1%
#2020000
0%
#2025000
0/
b0 :
1%
#2030000
0%
#2035000
b1 :
1%
#2040000
0%
#2045000
b10 :
1%
#2050000
0%
#2055000
b11 :
1%
#2060000
0%
#2065000
b100 :
1%
#2070000
0%
#2075000
b101 :
1%
#2080000
0%
#2085000
b110 :
1%
#2090000
0%
#2095000
b111 :
1%
#2100000
0%
#2105000
0@
1B
b1010 C
0T
14
b10101100 -
b10101100 H
b10101100 I
b10 .
b10 =
b10 D
b10 N
b10 K
b110 G
b10 8
b0 *
b0 M
b0 U
b0 F
b10 #
b10 '
b10 1
b10 5
b10 A
b10 E
b1100010 "
b1100010 (
b1100010 ,
b1100010 P
b1 0
b1 >
b1 R
b100 $
b100 &
b100 2
b100 6
b100 ?
b100 S
b11 !
b11 )
b11 +
b11 9
b11 ;
b11 O
1/
b1000 :
1%
#2110000
0%
#2115000
b1001 :
1%
#2120000
0%
#2125000
b1010 :
1%
#2130000
0%
#2135000
b1011 :
1%
#2140000
0%
#2145000
b1100 :
1%
#2150000
0%
#2155000
b1101 :
1%
#2160000
0%
#2165000
b1110 :
1%
#2170000
0%
#2175000
b1111 :
1%
#2180000
0%
#2185000
0/
b0 :
1%
#2190000
0%
#2195000
b1 :
1%
#2200000
0%
#2205000
b10 :
1%
#2210000
0%
#2215000
b11 :
1%
#2220000
0%
#2225000
b100 :
1%
#2230000
0%
#2235000
b101 :
1%
#2240000
0%
#2245000
b110 :
1%
#2250000
0%
#2255000
b111 :
1%
#2260000
0%
#2265000
13
1@
b100 *
b100 M
b100 U
b1111 #
b1111 '
b1111 1
b1111 5
b1111 A
b1111 E
b101 C
1T
17
b0 .
b0 =
b0 D
b0 N
b101011111 -
b101011111 H
b1011111 I
b0 K
b1100 G
b0 8
b11000000 "
b11000000 (
b11000000 ,
b11000000 P
b10 0
b10 >
b10 R
b100 !
b100 )
b100 +
b100 9
b100 ;
b100 O
1/
b1000 :
1%
#2270000
0%
#2275000
03
0@
b10 #
b10 '
b10 1
b10 5
b10 A
b10 E
b1010 C
07
b10 .
b10 =
b10 D
b10 N
b10101110 -
b10101110 H
b10101110 I
b10 K
b1000 G
b10 8
0/
b10000010 "
b10000010 (
b10000010 ,
b10000010 P
b0 :
b0 !
b0 )
b0 +
b0 9
b0 ;
b0 O
1%
#2280000
0%
#2285000
b1 :
1%
#2290000
0%
#2295000
b10 :
1%
#2300000
0%
#2305000
b11 :
1%
#2310000
0%
#2315000
b100 :
1%
#2320000
0%
#2325000
b101 :
1%
#2330000
0%
#2335000
b110 :
1%
#2340000
0%
#2345000
b111 :
1%
#2350000
0%
#2355000
b100 #
b100 '
b100 1
b100 5
b100 A
b100 E
04
1L
b100 .
b100 =
b100 D
b100 N
b10101010 I
b1010101010 -
b1010101010 H
b0 K
b1 G
b0 8
b10000 "
b10000 (
b10000 ,
b10000 P
b1 !
b1 )
b1 +
b1 9
b1 ;
b1 O
1/
b1000 :
1%
#2360000
0%
#2365000
b1001 :
1%
#2370000
0%
#2375000
b1010 :
1%
#2380000
0%
#2385000
b1011 :
1%
#2390000
0%
#2395000
b1100 :
1%
#2400000
0%
#2405000
b1101 :
1%
#2410000
0%
#2415000
b1110 :
1%
#2420000
0%
#2425000
b1111 :
1%
#2430000
0%
#2435000
0/
b0 :
1%
#2440000
0%
