ALU/src/ALU.sv
//try after to implement at logic level. Or pipelined
module ALU (
    input logic [3:0] sel,
    input logic [3:0] A,
    input logic [3:0] B,
    input logic M,
    input logic Cn,
    output logic [3:0] F,
    output logic ABFlag
);

    logic [3:0] Fin1, Fin2;
    always_comb begin
        if(M) begin
            case(sel)
                4'd0:Fin1 = ~A;
                4'd1:Fin1 = ~(A+B);
                4'd2:Fin1 = ~A & B;
                4'd3:Fin1 = 4'd0;
                4'd4:Fin1 = ~(A&B);
                4'd5:Fin1 = ~B;
                4'd6:Fin1 = A ^ B;
                4'd7:Fin1 = A & ~B;
                4'd8:Fin1 = ~A + B;
                4'd9:Fin1 = ~(A ^ B);
                4'd10:Fin1 = B;
                4'd11:Fin1 = A & B;
                4'd12:Fin1 = 4'd15;
                4'd13:Fin1 = (A + ~B);
                4'd14:Fin1 = A + B;
                4'd15:Fin1 = A;
            endcase
        end
        else begin
                case(sel)
                    4'd0:Fin2 = A;
                    4'd1:Fin2 = (A+B);
                    4'd2:Fin2 = A + ~B;
                    4'd3:Fin2 = 4'd15;
                    4'd4:Fin2 = A + (~A|B);
                    4'd5:Fin2 = (A+B) + (~A|B);
                    4'd6:Fin2 = (A-B)-1;
                    4'd7:Fin2 = (A&~B)-1;
                    4'd8:Fin2 = A + (A&B);
                    4'd9:Fin2 = (A + B);
                    4'd10:Fin2 = (A+ ~B) + (A&B);
                    4'd11:Fin2 = (A&B)-1;
                    4'd12:Fin2 = A + (A<<1);
                    4'd13:Fin2 = (A+B) + A;
                    4'd14:Fin2 = (A + ~B) + A;
                    4'd15:Fin2 = A-1;
                endcase
                if(Cn) Fin1 = Fin2;
                else Fin1 = Fin2 + 1;
            end
        end
        assign F = Fin1;
        assign ABFlag = (Fin1[0] & Fin1[1] & Fin1[2] & Fin1[3]);
endmodule

MUX/src/mux.sv
module mux (
    input logic sel,
    input logic [3:0] programP,
    input logic [3:0] Ram,
    input logic enable,
    output logic [3:0] outBits
);

always_comb begin
    if(enable) begin
        if(sel)
            outBits = Ram;
        else
            outBits = programP;
    end
    else outBits = 4'd0;
end


endmodule

RAM/RAM.sv
`timescale 1ns/1ps
module RAM
    (
        input logic write_en,
        input logic CS,
        input logic [3:0] addr,
        input logic [3:0] dataIN,
        output logic [3:0] dataOut
    );

    logic [3:0] dataCells [15:0];


    initial begin
    integer i;
        for (i = 0; i <= 15; i = i + 1) begin
            dataCells[i] = 4'd0;
        end
    end


    always_comb begin
        if(CS) begin
            if(~(write_en)) begin
                dataOut = 4'd0;
            end
            else begin
                dataOut = dataCells[addr];
            end
        end
    end

    always_latch begin
        if (CS && ~write_en) begin
            dataCells[addr] = dataIN;
        end
    end

endmodule

FF/src/FF.sv
module FF (
    input logic clk,
    input logic en,
    input logic [3:0] dIn,
    output logic [3:0] dOut
);
always_ff @(posedge clk) begin
    if(!en)
        dOut <= dIn;
    else
        dOut <= dOut;
end

endmodule

ControlROM/src/ControlROM.sv
module ControlROM (
    input logic [3:0] addr,
    output logic [9:0] prog
);


logic [7:0] progInt;

always_comb begin : progBlock
    case(addr)
        4'd0: progInt = 8'b10101010;
        4'd1: progInt = 8'b10101010;
        4'd2: progInt = 8'b10010010;
        4'd3: progInt = 8'b10010010;
        4'd4: progInt = 8'b01100010;
        4'd5: progInt = 8'b01100010;
        4'd6: progInt = 8'b10101100;
        4'd7: progInt = 8'b10101100;
        4'd8: progInt = 8'b10101110;
        4'd9: progInt = 8'b10101110;
        // 4'd10: do something with I/O pins
        // 4'd11:
        4'd12: progInt = 8'b01011111;
        4'd13: progInt = 8'b00001111;
        4'd14: progInt = 8'b11001111;
        4'd15: progInt = 8'b11001111;
        default: progInt = 8'd0;
    endcase
end 
assign prog[7:0] = progInt;
assign prog[8] = progInt[4];
assign prog[9] = addr[0];
endmodule

ProgramROM/ProgramROM.sv
`timescale 1ns/1ps
module ProgramROM (
    input logic [3:0] addr,
    output logic [7:0] prog
);

always_comb begin : progBlock
    case(addr)
        4'd0:prog = 8'h82;
        4'd1:prog = 8'h10;
        4'd2:prog = 8'h21;
        4'd3:prog = 8'h62;
        4'd4:prog = 8'hC0;
        default: prog = 8'h00;
    endcase
end 
endmodule

ProgramCounter/src/PC.sv

module PC(
    input logic clk,
    input logic progC,
    input logic [3:0] progP,
    input logic ABFlag,
    input logic [3:0] AccIn,
    output logic [3:0] programCount,
    output logic cp
);

logic [3:0]counter = 0;
logic [3:0] programCountint = 0;

always_ff @(posedge clk) begin : blockName
    if(progC && ABFlag) begin
        counter <= 0;
        programCountint <= progP;
    end else begin
        if(counter == 4'hF)
            counter <= 0;
        else
            counter <= counter + 1;
    end
end
always_ff @(posedge counter[3]) begin
    if(programCountint<15) 
    programCountint <= programCountint + 1;
    else
    programCountint <= 0;
end

assign cp = counter[3];
assign programCount = programCountint;


endmodule

TopLevel/src/TopLevel.sv
`include "ALU/src/ALU.sv"
`include "ControlROM/src/ControlROM.sv"
`include "ProgramCounter/src/PC.sv"
`include "RAM/src/RAM.sv"
`include "MUX/src/mux.sv"
`include "ProgramROM/src/ProgramROM.sv"
`include "FF/src/FF.sv"

module TopLevel(
    input logic clk,
    output logic [3:0] Acc,
    output logic [3:0] programCountOut,
    output logic [7:0] progPOut,
    output logic [9:0] progCOut,
    output logic [3:0] muxOutOut,
    output logic [3:0] addrOutOut,
    output logic [3:0] ramOutOut,
    output logic [3:0] AluOutOut,
    output logic cpOut,
    output logic ABFlagOut,
    output logic PCc0,
    output logic RWc1,
    output logic Accc2,
    output logic Mc3,
    output logic Cnc8,
    output logic S0c4,
    output logic S1c5,
    output logic S2c6,
    output logic S3c7,
    output logic Selc9
);

logic [3:0] programCount;
logic cp;
logic ABFlag;
logic [7:0] progP;
logic [9:0] progC;
logic [3:0] muxOut;
logic [3:0] addrOut;
logic [3:0] ramOut;
logic [3:0] AccOut;
logic [3:0] AluOut;

PC Pcblock(.clk(clk), .programCount(programCount), .cp(cp), .ABFlag(ABFlag), .progC(progC[0]), .progP(progP[3:0]));

ProgramROM programBlock (.prog(progP), .addr(programCount));

ControlROM controlBlock (.addr(progP[7:4]), .prog(progC));

FF addrBlock(.clk(cp), .en(1'd0), .dIn(muxOut), .dOut(addrOut));

FF AccBlock(.clk(cp), .en(progC[2]), .dIn(AluOut), .dOut(AccOut));

RAM ramBlock(.write_en(progC[1]), .CS(1'd1), .addr(addrOut), .dataOut(ramOut), .dataIN(AccOut));

mux muxblock (.programP(progP[3:0]), .sel(progC[9]), .Ram(ramOut), .enable(1'd1), .outBits(muxOut));

ALU aluBlock (.sel(progC[7:4]), .A(AccOut), .B(muxOut), .M(progC[3]), .Cn(progC[8]), .F(AluOut), .ABFlag(ABFlag));

assign Acc = AccOut;
assign ramOutOut = ramOut;
assign programCountOut = programCount;
assign AluOutOut = AluOut;
assign progPOut = progP;
assign muxOutOut = muxOut;
assign addrOutOut = addrOut;
assign cpOut = cp;
assign ABFlagOut = ABFlag;
assign progCOut = progC;
assign PCc0 = progC[0];
assign RWc1 = progC[1];
assign Accc2 = progC[2];
assign Mc3 = progC[3];
assign S0c4 = progC[4];
assign S1c5 = progC[5];
assign S2c6 = progC[6];
assign S3c7 = progC[7];
assign Cnc8 = progC[8];
assign Selc9 = progC[9];




endmodule

TopLevel/testB/TopLeveltestB.sv
`timescale 1ns/1ps
module TopLevelTestB;

    logic clk;
    logic ABFlagOut;
    logic cpOut;
    logic [3:0] Acc;
    logic [3:0] programCountOut;
    logic [3:0] AluOutOut;
    logic [9:0] progCOut;
    logic [7:0] progPOut;
    logic [3:0] ramOutOut;
    logic [3:0] addrOutOut;
    logic [3:0] muxOutOut;
    logic PCc0;
    logic RWc1;
    logic Accc2;
    logic Mc3;
    logic S0c4;
    logic S1c5;
    logic S2c6;
    logic S3c7;
    logic Cnc8;
    logic Selc9;

    TopLevel uut (.clk(clk), .Acc(Acc), .programCountOut(programCountOut), .AluOutOut(AluOutOut), 
    .progCOut(progCOut), .progPOut(progPOut), .muxOutOut(muxOutOut), .ramOutOut(ramOutOut), .addrOutOut(addrOutOut),
    .cpOut(cpOut), .ABFlagOut(ABFlagOut),
    .PCc0(PCc0),
    .RWc1(RWc1),
    .Accc2(Accc2),
    .Mc3(Mc3),
    .S0c4(S0c4),
    .S1c5(S1c5),
    .S2c6(S2c6),
    .S3c7(S3c7),
    .Cnc8(Cnc8),
    .Selc9(Selc9)
    );

    initial begin
        clk = 0;
        forever #5 clk = ~clk;
    end



    initial begin
        $dumpfile("curTest.vcd");
        $dumpvars(0,TopLevelTestB);
        #10000
        $finish;
    end
endmodule

curTest.vcd
$date
	Wed Feb  4 23:02:21 2026
$end
$version
	Icarus Verilog
$end
$timescale
	1ps
$end
$scope module TopLevelTestB $end
$var wire 4 ! ramOutOut [3:0] $end
$var wire 4 " programCountOut [3:0] $end
$var wire 8 # progPOut [7:0] $end
$var wire 10 $ progCOut [9:0] $end
$var wire 4 % muxOutOut [3:0] $end
$var wire 1 & cpOut $end
$var wire 4 ' addrOutOut [3:0] $end
$var wire 1 ( Selc9 $end
$var wire 1 ) S3c7 $end
$var wire 1 * S2c6 $end
$var wire 1 + S1c5 $end
$var wire 1 , S0c4 $end
$var wire 1 - RWc1 $end
$var wire 1 . PCc0 $end
$var wire 1 / Mc3 $end
$var wire 1 0 Cnc8 $end
$var wire 4 1 AluOutOut [3:0] $end
$var wire 1 2 Accc2 $end
$var wire 4 3 Acc [3:0] $end
$var wire 1 4 ABFlagOut $end
$var reg 1 5 clk $end
$scope module uut $end
$var wire 1 4 ABFlagOut $end
$var wire 4 6 Acc [3:0] $end
$var wire 4 7 AluOutOut [3:0] $end
$var wire 4 8 addrOutOut [3:0] $end
$var wire 1 5 clk $end
$var wire 1 & cpOut $end
$var wire 4 9 muxOutOut [3:0] $end
$var wire 10 : progCOut [9:0] $end
$var wire 8 ; progPOut [7:0] $end
$var wire 4 < programCountOut [3:0] $end
$var wire 4 = ramOutOut [3:0] $end
$var wire 4 > ramOut [3:0] $end
$var wire 4 ? programCount [3:0] $end
$var wire 8 @ progP [7:0] $end
$var wire 10 A progC [9:0] $end
$var wire 4 B muxOut [3:0] $end
$var wire 1 C cp $end
$var wire 4 D addrOut [3:0] $end
$var wire 1 ( Selc9 $end
$var wire 1 ) S3c7 $end
$var wire 1 * S2c6 $end
$var wire 1 + S1c5 $end
$var wire 1 , S0c4 $end
$var wire 1 - RWc1 $end
$var wire 1 . PCc0 $end
$var wire 1 / Mc3 $end
$var wire 1 0 Cnc8 $end
$var wire 4 E AluOut [3:0] $end
$var wire 1 2 Accc2 $end
$var wire 4 F AccOut [3:0] $end
$var wire 1 G ABFlag $end
$scope module AccBlock $end
$var wire 1 H en $end
$var wire 4 I dIn [3:0] $end
$var wire 1 C clk $end
$var reg 4 J dOut [3:0] $end
$upscope $end
$scope module Pcblock $end
$var wire 4 K AccIn [3:0] $end
$var wire 1 5 clk $end
$var wire 1 L progC $end
$var wire 4 M progP [3:0] $end
$var wire 4 N programCount [3:0] $end
$var wire 1 C cp $end
$var wire 1 G ABFlag $end
$var reg 4 O counter [3:0] $end
$var reg 4 P programCountint [3:0] $end
$scope begin blockName $end
$upscope $end
$upscope $end
$scope module addrBlock $end
$var wire 1 C clk $end
$var wire 1 Q en $end
$var wire 4 R dIn [3:0] $end
$var reg 4 S dOut [3:0] $end
$upscope $end
$scope module aluBlock $end
$var wire 4 T A [3:0] $end
$var wire 1 G ABFlag $end
$var wire 1 U Cn $end
$var wire 4 V F [3:0] $end
$var wire 1 W M $end
$var wire 4 X sel [3:0] $end
$var wire 4 Y B [3:0] $end
$var reg 4 Z Fin1 [3:0] $end
$var reg 4 [ Fin2 [3:0] $end
$upscope $end
$scope module controlBlock $end
$var wire 4 \ addr [3:0] $end
$var wire 10 ] prog [9:0] $end
$var reg 8 ^ progInt [7:0] $end
$scope begin progBlock $end
$upscope $end
$upscope $end
$scope module muxblock $end
$var wire 1 _ enable $end
$var wire 4 ` programP [3:0] $end
$var wire 1 a sel $end
$var wire 4 b Ram [3:0] $end
$var reg 4 c outBits [3:0] $end
$upscope $end
$scope module programBlock $end
$var wire 4 d addr [3:0] $end
$var reg 8 e prog [7:0] $end
$scope begin progBlock $end
$upscope $end
$upscope $end
$scope module ramBlock $end
$var wire 1 f CS $end
$var wire 4 g addr [3:0] $end
$var wire 4 h dataIN [3:0] $end
$var wire 1 i write_en $end
$var reg 4 j dataOut [3:0] $end
$scope begin $unm_blk_7 $end
$var integer 32 k i [31:0] $end
$upscope $end
$upscope $end
$upscope $end
$upscope $end
$enddefinitions $end
$comment Show the parameter values. $end
$dumpall
$end
#0
$dumpvars
b10000 k
bx j
1i
bx h
bx g
1f
b10000010 e
b0 d
b10 c
bx b
0a
b10 `
1_
b10101110 ^
b10101110 ]
b1000 \
bx [
b10 Z
b10 Y
b1010 X
1W
b10 V
0U
bx T
bx S
b10 R
0Q
b0 P
b0 O
b0 N
b10 M
0L
bz K
bx J
b10 I
1H
0G
bx F
b10 E
bx D
0C
b10 B
b10101110 A
b10000010 @
b0 ?
bx >
bx =
b0 <
b10000010 ;
b10101110 :
b10 9
bx 8
b10 7
bx 6
05
04
bx 3
12
b10 1
00
1/
0.
1-
0,
1+
0*
1)
0(
bx '
0&
b10 %
b10101110 $
b10000010 #
b0 "
bx !
$end
#5000
b1 O
15
#10000
05
#15000
b10 O
15
#20000
05
#25000
b11 O
15
#30000
05
#35000
b100 O
15
#40000
05
#45000
b101 O
15
#50000
05
#55000
b110 O
15
#60000
05
#65000
b111 O
15
#70000
05
#75000
02
0H
1(
1a
b0 1
b0 7
b0 E
b0 I
b0 V
b0 Z
b10101010 ^
b1010101010 $
b1010101010 :
b1010101010 A
b1010101010 ]
b0 %
b0 9
b0 B
b0 R
b0 Y
b0 c
b0 `
b1 \
b0 M
b0 !
b0 =
b0 >
b0 b
b0 j
b10000 #
b10000 ;
b10000 @
b10000 e
b10 '
b10 8
b10 D
b10 S
b10 g
b1 "
b1 <
b1 ?
b1 N
b1 P
b1 d
1&
1C
b1000 O
15
#80000
05
#85000
b1001 O
15
#90000
05
#95000
b1010 O
15
#100000
05
#105000
b1011 O
15
#110000
05
#115000
b1100 O
15
#120000
05
#125000
b1101 O
15
#130000
05
#135000
b1110 O
15
#140000
05
#145000
b1111 O
15
#150000
05
#155000
0&
0C
b0 O
15
#160000
05
#165000
b1 O
15
#170000
05
#175000
b10 O
15
#180000
05
#185000
b11 O
15
#190000
05
#195000
b100 O
15
#200000
05
#205000
b101 O
15
#210000
05
#215000
b110 O
15
#220000
05
#225000
b111 O
15
#230000
05
#235000
10
1U
b1 1
b1 7
b1 E
b1 I
b1 V
b1 Z
b1 [
b1 %
b1 9
b1 B
b1 R
b1 Y
b1 c
0+
1,
0/
0W
b1001 X
0(
0a
b10010010 ^
b110010010 $
b110010010 :
b110010010 A
b110010010 ]
b1 `
b10 \
b1 M
b100001 #
b100001 ;
b100001 @
b100001 e
b0 3
b0 6
b0 F
b0 J
b0 T
b0 h
b0 '
b0 8
b0 D
b0 S
b0 g
b10 "
b10 <
b10 ?
b10 N
b10 P
b10 d
1&
1C
b1000 O
15
#240000
05
#245000
b1001 O
15
#250000
05
#255000
b1010 O
15
#260000
05
#265000
b1011 O
15
#270000
05
#275000
b1100 O
15
#280000
05
#285000
b1101 O
15
#290000
05
#295000
b1110 O
15
#300000
05
#305000
b1111 O
15
#310000
05
#315000
0&
0C
b0 O
15
#320000
05
#325000
b1 O
15
#330000
05
#335000
b10 O
15
#340000
05
#345000
b11 O
15
#350000
05
#355000
b100 O
15
#360000
05
#365000
b101 O
15
#370000
05
#375000
b110 O
15
#380000
05
#385000
b111 O
15
#390000
05
#395000
00
0U
1+
0,
1/
12
0-
1W
b1010 X
0i
1H
b10 %
b10 9
b10 B
b10 R
b10 Y
b10 c
b10101100 $
b10101100 :
b10101100 A
b10101100 ]
b10101100 ^
b10 `
b110 \
b10 M
b10 1
b10 7
b10 E
b10 I
b10 V
b10 Z
b10 [
b1100010 #
b1100010 ;
b1100010 @
b1100010 e
b1 '
b1 8
b1 D
b1 S
b1 g
b1 3
b1 6
b1 F
b1 J
b1 T
b1 h
b11 "
b11 <
b11 ?
b11 N
b11 P
b11 d
1&
1C
b1000 O
15
#400000
05
#405000
b1001 O
15
#410000
05
#415000
b1010 O
15
#420000
05
#425000
b1011 O
15
#430000
05
#435000
b1100 O
15
#440000
05
#445000
b1101 O
15
#450000
05
#455000
b1110 O
15
#460000
05
#465000
b1111 O
15
#470000
05
#475000
0&
0C
b0 O
15
#480000
05
#485000
b1 O
15
#490000
05
#495000
b10 O
15
#500000
05
#505000
b11 O
15
#510000
05
#515000
b100 O
15
#520000
05
#525000
b101 O
15
#530000
05
#535000
b110 O
15
#540000
05
#545000
b111 O
15
#550000
05
#555000
14
1G
10
1U
b1 !
b1 =
b1 >
b1 b
b1 j
b1111 1
b1111 7
b1111 E
b1111 I
b1111 V
b1111 Z
0)
1*
0+
1,
1-
1.
b101 X
1i
1L
b0 %
b0 9
b0 B
b0 R
b0 Y
b0 c
b101011111 $
b101011111 :
b101011111 A
b101011111 ]
b1011111 ^
b0 `
b1100 \
b0 M
b11000000 #
b11000000 ;
b11000000 @
b11000000 e
b10 '
b10 8
b10 D
b10 S
b10 g
b100 "
b100 <
b100 ?
b100 N
b100 P
b100 d
1&
1C
b1000 O
15
#560000
05
#565000
04
0G
00
0U
b10 1
b10 7
b10 E
b10 I
b10 V
b10 Z
1)
0*
1+
0,
0.
b1010 X
0L
b10 %
b10 9
b10 B
b10 R
b10 Y
b10 c
b10101110 $
b10101110 :
b10101110 A
b10101110 ]
b10101110 ^
b10 `
b1000 \
b10 M
b10000010 #
b10000010 ;
b10000010 @
b10000010 e
0&
0C
b0 "
b0 <
b0 ?
b0 N
b0 P
b0 d
b0 O
15
#570000
05
#575000
b1 O
15
#580000
05
#585000
b10 O
15
#590000
05
#595000
b11 O
15
#600000
05
#605000
b100 O
15
#610000
05
#615000
b101 O
15
#620000
05
#625000
b110 O
15
#630000
05
#635000
b111 O
15
#640000
05
#645000
b1 1
b1 7
b1 E
b1 I
b1 V
b1 Z
02
0H
1(
1a
b1 %
b1 9
b1 B
b1 R
b1 Y
b1 c
b10101010 ^
b1010101010 $
b1010101010 :
b1010101010 A
b1010101010 ]
b0 `
b1 \
b0 M
b10000 #
b10000 ;
b10000 @
b10000 e
b1 "
b1 <
b1 ?
b1 N
b1 P
b1 d
1&
1C
b1000 O
15
#650000
05
#655000
b1001 O
15
#660000
05
#665000
b1010 O
15
#670000
05
#675000
b1011 O
15
#680000
05
#685000
b1100 O
15
#690000
05
#695000
b1101 O
15
#700000
05
#705000
b1110 O
15
#710000
05
#715000
b1111 O
15
#720000
05
#725000
0&
0C
b0 O
15
#730000
05
#735000
b1 O
15
#740000
05
#745000
b10 O
15
#750000
05
#755000
b11 O
15
#760000
05
#765000
b100 O
15
#770000
05
#775000
b101 O
15
#780000
05
#785000
b110 O
15
#790000
05
#795000
b111 O
15
#800000
05
#805000
10
1U
b10 1
b10 7
b10 E
b10 I
b10 V
b10 Z
0+
1,
0/
0W
b1001 X
0(
0a
b10010010 ^
b110010010 $
b110010010 :
b110010010 A
b110010010 ]
b1 `
b10 \
b1 M
b100001 #
b100001 ;
b100001 @
b100001 e
b1 '
b1 8
b1 D
b1 S
b1 g
b10 "
b10 <
b10 ?
b10 N
b10 P
b10 d
1&
1C
b1000 O
15
#810000
05
#815000
b1001 O
15
#820000
05
#825000
b1010 O
15
#830000
05
#835000
b1011 O
15
#840000
05
#845000
b1100 O
15
#850000
05
#855000
b1101 O
15
#860000
05
#865000
b1110 O
15
#870000
05
#875000
b1111 O
15
#880000
05
#885000
0&
0C
b0 O
15
#890000
05
#895000
b1 O
15
#900000
05
#905000
b10 O
15
#910000
05
#915000
b11 O
15
#920000
05
#925000
b100 O
15
#930000
05
#935000
b101 O
15
#940000
05
#945000
b110 O
15
#950000
05
#955000
b111 O
15
#960000
05
#965000
00
0U
1+
0,
1/
12
0-
1W
b1010 X
0i
1H
b10 %
b10 9
b10 B
b10 R
b10 Y
b10 c
b10101100 $
b10101100 :
b10101100 A
b10101100 ]
b10101100 ^
b10 `
b110 \
b10 M
b10 1
b10 7
b10 E
b10 I
b10 V
b10 Z
b11 [
b1100010 #
b1100010 ;
b1100010 @
b1100010 e
b10 3
b10 6
b10 F
b10 J
b10 T
b10 h
b11 "
b11 <
b11 ?
b11 N
b11 P
b11 d
1&
1C
b1000 O
15
#970000
05
#975000
b1001 O
15
#980000
05
#985000
b1010 O
15
#990000
05
#995000
b1011 O
15
#1000000
05
#1005000
b1100 O
15
#1010000
05
#1015000
b1101 O
15
#1020000
05
#1025000
b1110 O
15
#1030000
05
#1035000
b1111 O
15
#1040000
05
#1045000
0&
0C
b0 O
15
#1050000
05
#1055000
b1 O
15
#1060000
05
#1065000
b10 O
15
#1070000
05
#1075000
b11 O
15
#1080000
05
#1085000
b100 O
15
#1090000
05
#1095000
b101 O
15
#1100000
05
#1105000
b110 O
15
#1110000
05
#1115000
b111 O
15
#1120000
05
#1125000
14
1G
10
1U
b10 !
b10 =
b10 >
b10 b
b10 j
b1111 1
b1111 7
b1111 E
b1111 I
b1111 V
b1111 Z
0)
1*
0+
1,
1-
1.
b101 X
1i
1L
b0 %
b0 9
b0 B
b0 R
b0 Y
b0 c
b101011111 $
b101011111 :
b101011111 A
b101011111 ]
b1011111 ^
b0 `
b1100 \
b0 M
b11000000 #
b11000000 ;
b11000000 @
b11000000 e
b10 '
b10 8
b10 D
b10 S
b10 g
b100 "
b100 <
b100 ?
b100 N
b100 P
b100 d
1&
1C
b1000 O
15
#1130000
05
#1135000
04
0G
00
0U
b10 1
b10 7
b10 E
b10 I
b10 V
b10 Z
1)
0*
1+
0,
0.
b1010 X
0L
b10 %
b10 9
b10 B
b10 R
b10 Y
b10 c
b10101110 $
b10101110 :
b10101110 A
b10101110 ]
b10101110 ^
b10 `
b1000 \
b10 M
b10000010 #
b10000010 ;
b10000010 @
b10000010 e
0&
0C
b0 "
b0 <
b0 ?
b0 N
b0 P
b0 d
b0 O
15
#1140000
05
#1145000
b1 O
15
#1150000
05
#1155000
b10 O
15
#1160000
05
#1165000
b11 O
15
#1170000
05
#1175000
b100 O
15
#1180000
05
#1185000
b101 O
15
#1190000
05
#1195000
b110 O
15
#1200000
05
#1205000
b111 O
15
#1210000
05
#1215000
b10 1
b10 7
b10 E
b10 I
b10 V
b10 Z
02
0H
1(
1a
b10 %
b10 9
b10 B
b10 R
b10 Y
b10 c
b10101010 ^
b1010101010 $
b1010101010 :
b1010101010 A
b1010101010 ]
b0 `
b1 \
b0 M
b10000 #
b10000 ;
b10000 @
b10000 e
b1 "
b1 <
b1 ?
b1 N
b1 P
b1 d
1&
1C
b1000 O
15
#1220000
05
#1225000
b1001 O
15
#1230000
05
#1235000
b1010 O
15
#1240000
05
#1245000
b1011 O
15
#1250000
05
#1255000
b1100 O
15
#1260000
05
#1265000
b1101 O
15
#1270000
05
#1275000
b1110 O
15
#1280000
05
#1285000
b1111 O
15
#1290000
05
#1295000
0&
0C
b0 O
15
#1300000
05
#1305000
b1 O
15
#1310000
05
#1315000
b10 O
15
#1320000
05
#1325000
b11 O
15
#1330000
05
#1335000
b100 O
15
#1340000
05
#1345000
b101 O
15
#1350000
05
#1355000
b110 O
15
#1360000
05
#1365000
b111 O
15
#1370000
05
#1375000
10
1U
b11 1
b11 7
b11 E
b11 I
b11 V
b11 Z
b1 %
b1 9
b1 B
b1 R
b1 Y
b1 c
0+
1,
0/
0W
b1001 X
0(
0a
b10010010 ^
b110010010 $
b110010010 :
b110010010 A
b110010010 ]
b1 `
b10 \
b1 M
b100001 #
b100001 ;
b100001 @
b100001 e
b10 "
b10 <
b10 ?
b10 N
b10 P
b10 d
1&
1C
b1000 O
15
#1380000
05
#1385000
b1001 O
15
#1390000
05
#1395000
b1010 O
15
#1400000
05
#1405000
b1011 O
15
#1410000
05
#1415000
b1100 O
15
#1420000
05
#1425000
b1101 O
15
#1430000
05
#1435000
b1110 O
15
#1440000
05
#1445000
b1111 O
15
#1450000
05
#1455000
0&
0C
b0 O
15
#1460000
05
#1465000
b1 O
15
#1470000
05
#1475000
b10 O
15
#1480000
05
#1485000
b11 O
15
#1490000
05
#1495000
b100 O
15
#1500000
05
#1505000
b101 O
15
#1510000
05
#1515000
b110 O
15
#1520000
05
#1525000
b111 O
15
#1530000
05
#1535000
00
0U
1+
0,
1/
12
0-
1W
b1010 X
0i
1H
b10 %
b10 9
b10 B
b10 R
b10 Y
b10 c
b10101100 $
b10101100 :
b10101100 A
b10101100 ]
b10101100 ^
b10 `
b110 \
b10 M
b10 1
b10 7
b10 E
b10 I
b10 V
b10 Z
b100 [
b1100010 #
b1100010 ;
b1100010 @
b1100010 e
b1 '
b1 8
b1 D
b1 S
b1 g
b11 3
b11 6
b11 F
b11 J
b11 T
b11 h
b11 "
b11 <
b11 ?
b11 N
b11 P
b11 d
1&
1C
b1000 O
15
#1540000
05
#1545000
b1001 O
15
#1550000
05
#1555000
b1010 O
15
#1560000
05
#1565000
b1011 O
15
#1570000
05
#1575000
b1100 O
15
#1580000
05
#1585000
b1101 O
15
#1590000
05
#1595000
b1110 O
15
#1600000
05
#1605000
b1111 O
15
#1610000
05
#1615000
0&
0C
b0 O
15
#1620000
05
#1625000
b1 O
15
#1630000
05
#1635000
b10 O
15
#1640000
05
#1645000
b11 O
15
#1650000
05
#1655000
b100 O
15
#1660000
05
#1665000
b101 O
15
#1670000
05
#1675000
b110 O
15
#1680000
05
#1685000
b111 O
15
#1690000
05
#1695000
14
1G
10
1U
b11 !
b11 =
b11 >
b11 b
b11 j
b1111 1
b1111 7
b1111 E
b1111 I
b1111 V
b1111 Z
0)
1*
0+
1,
1-
1.
b101 X
1i
1L
b0 %
b0 9
b0 B
b0 R
b0 Y
b0 c
b101011111 $
b101011111 :
b101011111 A
b101011111 ]
b1011111 ^
b0 `
b1100 \
b0 M
b11000000 #
b11000000 ;
b11000000 @
b11000000 e
b10 '
b10 8
b10 D
b10 S
b10 g
b100 "
b100 <
b100 ?
b100 N
b100 P
b100 d
1&
1C
b1000 O
15
#1700000
05
#1705000
04
0G
00
0U
b10 1
b10 7
b10 E
b10 I
b10 V
b10 Z
1)
0*
1+
0,
0.
b1010 X
0L
b10 %
b10 9
b10 B
b10 R
b10 Y
b10 c
b10101110 $
b10101110 :
b10101110 A
b10101110 ]
b10101110 ^
b10 `
b1000 \
b10 M
b10000010 #
b10000010 ;
b10000010 @
b10000010 e
0&
0C
b0 "
b0 <
b0 ?
b0 N
b0 P
b0 d
b0 O
15
#1710000
05
#1715000
b1 O
15
#1720000
05
#1725000
b10 O
15
#1730000
05
#1735000
b11 O
15
#1740000
05
#1745000
b100 O
15
#1750000
05
#1755000
b101 O
15
#1760000
05
#1765000
b110 O
15
#1770000
05
#1775000
b111 O
15
#1780000
05
#1785000
b11 1
b11 7
b11 E
b11 I
b11 V
b11 Z
02
0H
1(
1a
b11 %
b11 9
b11 B
b11 R
b11 Y
b11 c
b10101010 ^
b1010101010 $
b1010101010 :
b1010101010 A
b1010101010 ]
b0 `
b1 \
b0 M
b10000 #
b10000 ;
b10000 @
b10000 e
b1 "
b1 <
b1 ?
b1 N
b1 P
b1 d
1&
1C
b1000 O
15
#1790000
05
#1795000
b1001 O
15
#1800000
05
#1805000
b1010 O
15
#1810000
05
#1815000
b1011 O
15
#1820000
05
#1825000
b1100 O
15
#1830000
05
#1835000
b1101 O
15
#1840000
05
#1845000
b1110 O
15
#1850000
05
#1855000
b1111 O
15
#1860000
05
#1865000
0&
0C
b0 O
15
#1870000
05
#1875000
b1 O
15
#1880000
05
#1885000
b10 O
15
#1890000
05
#1895000
b11 O
15
#1900000
05
#1905000
b100 O
15
#1910000
05
#1915000
b101 O
15
#1920000
05
#1925000
b110 O
15
#1930000
05
#1935000
b111 O
15
#1940000
05
#1945000
10
1U
0+
1,
0/
0W
b1001 X
0(
0a
b100 1
b100 7
b100 E
b100 I
b100 V
b100 Z
b10010010 ^
b110010010 $
b110010010 :
b110010010 A
b110010010 ]
b1 %
b1 9
b1 B
b1 R
b1 Y
b1 c
b1 `
b10 \
b1 M
b0 !
b0 =
b0 >
b0 b
b0 j
b100001 #
b100001 ;
b100001 @
b100001 e
b11 '
b11 8
b11 D
b11 S
b11 g
b10 "
b10 <
b10 ?
b10 N
b10 P
b10 d
1&
1C
b1000 O
15
#1950000
05
#1955000
b1001 O
15
#1960000
05
#1965000
b1010 O
15
#1970000
05
#1975000
b1011 O
15
#1980000
05
#1985000
b1100 O
15
#1990000
05
#1995000
b1101 O
15
#2000000
05
#2005000
b1110 O
15
#2010000
05
#2015000
b1111 O
15
#2020000
05
#2025000
0&
0C
b0 O
15
#2030000
05
#2035000
b1 O
15
#2040000
05
#2045000
b10 O
15
#2050000
05
#2055000
b11 O
15
#2060000
05
#2065000
b100 O
15
#2070000
05
#2075000
b101 O
15
#2080000
05
#2085000
b110 O
15
#2090000
05
#2095000
b111 O
15
#2100000
05
#2105000
00
0U
1+
0,
1/
12
0-
1W
b1010 X
0i
1H
b10101100 $
b10101100 :
b10101100 A
b10101100 ]
b10101100 ^
b10 %
b10 9
b10 B
b10 R
b10 Y
b10 c
b10 `
b110 \
b10 M
b10 1
b10 7
b10 E
b10 I
b10 V
b10 Z
b110 [
b11 !
b11 =
b11 >
b11 b
b11 j
b1100010 #
b1100010 ;
b1100010 @
b1100010 e
b1 '
b1 8
b1 D
b1 S
b1 g
b100 3
b100 6
b100 F
b100 J
b100 T
b100 h
b11 "
b11 <
b11 ?
b11 N
b11 P
b11 d
1&
1C
b1000 O
15
#2110000
05
#2115000
b1001 O
15
