ALU/src/ALU.sv
//try after to implement at logic level. Or pipelined
module ALU (
    input logic [3:0] sel,
    input logic [3:0] A,
    input logic [3:0] B,
    input logic M,
    input logic Cn,
    output logic [3:0] F,
    output logic ABFlag
);

    logic [3:0] Fin;
    always_comb begin
        if(M) begin
            case(sel)
                4'd0:F = ~A;
                4'd1:F = ~(A+B);
                4'd2:F = ~A & B;
                4'd3:F = 4'd0;
                4'd4:F = ~(A&B);
                4'd5:F = ~B;
                4'd6:F = A ^ B;
                4'd7:F = A & ~B;
                4'd8:F = ~A + B;
                4'd9:F = ~(A ^ B);
                4'd10:F = B;
                4'd11:F = A & B;
                4'd12:F = 4'd15;
                4'd13:F = (A + ~B);
                4'd14:F = A + B;
                4'd15:F = A;
            endcase
        end
        else begin
                case(sel)
                    4'd0:Fin = A;
                    4'd1:Fin = (A+B);
                    4'd2:Fin = A + ~B;
                    4'd3:Fin = 4'd15;
                    4'd4:Fin = A + (~A|B);
                    4'd5:Fin = (A+B) + (~A|B);
                    4'd6:Fin = (A-B)-1;
                    4'd7:Fin = (A&~B)-1;
                    4'd8:Fin = A + (A&B);
                    4'd9:Fin = (A + B);
                    4'd10:Fin = (A+ ~B) + (A&B);
                    4'd11:Fin = (A&B)-1;
                    4'd12:Fin = A + (A<<1);
                    4'd13:Fin = (A+B) + A;
                    4'd14:Fin = (A + ~B) + A;
                    4'd15:Fin = A-1;
                endcase
                if(Cn) F = Fin;
                else F = Fin + 1;
            end
        end
        assign ABFlag = (Fin[0] & Fin[1] & Fin[2] & Fin[3]);
endmodule

MUX/src/mux.sv
module mux (
    input logic sel,
    input logic [3:0] programP,
    input logic [3:0] Ram,
    input logic enable,
    output logic [3:0] outBits
);

always_comb begin
    if(enable) begin
        if(sel)
            outBits = Ram;
        else
            outBits = programP;
    end
    else outBits = 4'd0;
end


endmodule

RAM/src/RAM.sv
module RAM
    (
        input logic write_en,
        input logic CS,
        input logic [3:0] addr,
        input logic [3:0] dataIN,
        output logic [3:0] dataOut
    );

    logic [3:0] dataCells [15:0];


    always_comb begin
        if(CS) begin
            if(write_en) begin
                dataCells[addr] = dataIN;
            end
            else begin
                dataOut = dataCells[addr];
            end
        end
    end

endmodule

Addr/src/Addr.sv
module Addr (
    input logic clk,
    input logic en,
    input logic [3:0] dIn,
    output logic [3:0] dOut
);

always_ff @(posedge clk) begin
    if(en)
        dOut <= dIn;
    else
        dOut <= 4'd0;
end
endmodule

ControlROM/src/ControlROM.sv
module ControlROM (
    input logic [3:0] addr,
    output logic [9:0] prog
);


logic [7:0] progInt;

always_comb begin : progBlock
    case(addr)
        4'd0: progInt = 8'b10101010;
        4'd1: progInt = 8'b10101010;
        4'd2: progInt = 8'b10010010;
        4'd3: progInt = 8'b10010010;
        4'd4: progInt = 8'b01100010;
        4'd5: progInt = 8'b01100010;
        4'd6: progInt = 8'b10101100;
        4'd7: progInt = 8'b10101100;
        4'd8: progInt = 8'b10101110;
        4'd9: progInt = 8'b10101110;
        // 4'd10: do something with I/O pins
        // 4'd11:
        4'd12: progInt = 8'b00001111;
        4'd13: progInt = 8'b00001111;
        4'd14: progInt = 8'b11001111;
        4'd15: progInt = 8'b11001111;
        default: progInt = 8'd0;
    endcase
end 
assign prog[7:0] = progInt;
assign prog[8] = progInt[4];
assign prog[9] = addr[0];
endmodule

ProgramROM/ProgramROM.sv
`timescale 1ns/1ps
module ProgramROM (
    input logic [3:0] addr,
    output logic [7:0] prog
);

always_comb begin : progBlock
    case(addr)
        4'd0:prog = 8'h82;
        4'd1:prog = 8'h10;
        4'd2:prog = 8'h21;
        4'd3:prog = 8'h62;
        4'd4:prog = 8'hC0;
        default: prog = 8'h00;
    endcase
end 
endmodule

ProgramCounter/src/PC.sv

module PC(
    input logic clk,
    input logic progC,
    input logic [3:0] progP,
    input logic ABFlag,
    input logic [3:0] AccIn,
    output logic [3:0] programCount,
    output logic cp
);

logic [19:0]counter = 0;
logic [3:0] programCountint = 0;

always_ff @(posedge clk) begin : blockName
    if(progC && ABFlag) begin
        counter <= 0;
        programCountint <= progP;
    end else begin
        if(counter == 20'hFFFFF)
            counter <= 0;
        else
            counter = counter + 1;
    
        if(counter[1]) programCountint <= programCountint + 1;
    end
end
assign cp = counter[1];
assign programCount = programCountint;


endmodule

TopLevel/src/TopLevel.sv
`include "ALU/src/ALU.sv"
`include "ControlROM/src/ControlROM.sv"
`include "ProgramCounter/src/PC.sv"
`include "RAM/src/RAM.sv"
`include "MUX/src/mux.sv"
`include "ProgramROM/src/ProgramROM.sv"
`include "Addr/src/Addr.sv"

module TopLevel(
    input logic clk,
    output logic [3:0] Acc
);

logic [3:0] programCount;
logic cp;
logic ABFlag;
logic [7:0] progP;
logic [9:0] progC;
logic [3:0] muxOut;
logic [3:0] addrOut;
logic [3:0] ramOut;
logic [3:0] AccOut;
logic [3:0] AluOut;

PC Pcblock(.clk(clk), .programCount(programCount), .cp(cp), .ABFlag(ABFlag), .progC(progC[0]), .progP(progP[3:0]));

ProgramROM programBlock (.prog(progP), .addr(programCount));

ControlROM controlBlock (.addr(progP[3:0]), .prog(progC));

Addr addrBlock(.clk(cp), .en(1'd1), .dIn(muxOut), .dOut(addrOut));

Addr AccBlock(.clk(cp), .en(1'd1), .dIn(AluOut), .dOut(AccOut));

RAM ramBlock(.write_en(progC[1]), .CS(1'd1), .addr(addrOut), .dataOut(ramOut), .dataIN(AccOut));

mux muxblock (.programP(progP[3:0]), .sel(progC[9]), .Ram(ramOut), .enable(1'd1), .outBits(muxOut));

ALU aluBlock (.sel(progC[7:4]), .A(AccOut), .B(muxOut), .M(progC[3]), .Cn(progC[8]), .F(AluOut), .ABFlag(ABFlag));

assign Acc = AccOut;


endmodule

TopLevel/testB/TopLeveltestB.sv
`timescale 1ns/1ps
module TopLevelTestB;

    logic clk;
    logic [3:0] Acc;

    TopLevel uut (.clk(clk), .Acc(Acc));

    initial begin
        clk = 0;
        forever #5 clk = ~clk;
    end



    initial begin
        $dumpfile("curTest.vcd");
        $dumpvars(0,TopLevelTestB);
        #10000
        $finish;
    end
endmodule

curTest.vcd
$date
	Wed Feb  4 09:57:28 2026
$end
$version
	Icarus Verilog
$end
$timescale
	1ps
$end
$scope module TopLevelTestB $end
$var wire 4 ! Acc [3:0] $end
$var reg 1 " clk $end
$scope module uut $end
$var wire 4 # Acc [3:0] $end
$var wire 1 " clk $end
$var wire 4 $ ramOut [3:0] $end
$var wire 4 % programCount [3:0] $end
$var wire 8 & progP [7:0] $end
$var wire 10 ' progC [9:0] $end
$var wire 4 ( muxOut [3:0] $end
$var wire 1 ) cp $end
$var wire 4 * addrOut [3:0] $end
$var wire 4 + AluOut [3:0] $end
$var wire 4 , AccOut [3:0] $end
$var wire 1 - ABFlag $end
$scope module AccBlock $end
$var wire 1 . en $end
$var wire 4 / dIn [3:0] $end
$var wire 1 ) clk $end
$var reg 4 0 dOut [3:0] $end
$upscope $end
$scope module Pcblock $end
$var wire 4 1 AccIn [3:0] $end
$var wire 1 " clk $end
$var wire 1 2 progC $end
$var wire 4 3 progP [3:0] $end
$var wire 4 4 programCount [3:0] $end
$var wire 1 ) cp $end
$var wire 1 - ABFlag $end
$var reg 20 5 counter [19:0] $end
$var reg 4 6 programCountint [3:0] $end
$scope begin blockName $end
$upscope $end
$upscope $end
$scope module addrBlock $end
$var wire 1 ) clk $end
$var wire 1 7 en $end
$var wire 4 8 dIn [3:0] $end
$var reg 4 9 dOut [3:0] $end
$upscope $end
$scope module aluBlock $end
$var wire 4 : A [3:0] $end
$var wire 1 - ABFlag $end
$var wire 1 ; Cn $end
$var wire 1 < M $end
$var wire 4 = sel [3:0] $end
$var wire 4 > B [3:0] $end
$var reg 4 ? F [3:0] $end
$var reg 4 @ Fin [3:0] $end
$upscope $end
$scope module controlBlock $end
$var wire 4 A addr [3:0] $end
$var wire 10 B prog [9:0] $end
$var reg 8 C progInt [7:0] $end
$scope begin progBlock $end
$upscope $end
$upscope $end
$scope module muxblock $end
$var wire 1 D enable $end
$var wire 4 E programP [3:0] $end
$var wire 1 F sel $end
$var wire 4 G Ram [3:0] $end
$var reg 4 H outBits [3:0] $end
$upscope $end
$scope module programBlock $end
$var wire 4 I addr [3:0] $end
$var reg 8 J prog [7:0] $end
$scope begin progBlock $end
$upscope $end
$upscope $end
$scope module ramBlock $end
$var wire 1 K CS $end
$var wire 4 L addr [3:0] $end
$var wire 4 M dataIN [3:0] $end
$var wire 1 N write_en $end
$var reg 4 O dataOut [3:0] $end
$upscope $end
$upscope $end
$upscope $end
$enddefinitions $end
$comment Show the parameter values. $end
$dumpall
$end
#0
$dumpvars
bx O
1N
bx M
bx L
1K
b10000010 J
b0 I
b10 H
bx G
0F
b10 E
1D
b10010010 C
b110010010 B
b10 A
bx @
bx ?
b10 >
b1001 =
0<
1;
bx :
bx 9
b10 8
17
b0 6
b0 5
b0 4
b10 3
02
bz 1
bx 0
bx /
1.
x-
bx ,
bx +
bx *
0)
b10 (
b110010010 '
b10000010 &
b0 %
bx $
bx #
0"
bx !
$end
#5000
b1 5
1"
#10000
0"
#15000
0;
b0 +
b0 /
b0 ?
1<
b1010 =
b0 (
b0 8
b0 >
b0 H
b10101010 '
b10101010 B
b10101010 C
b0 E
b0 A
b0 3
b10000 &
b10000 J
b10 *
b10 9
b10 L
b1 %
b1 4
b1 I
b1 6
1)
b10 5
1"
#20000
0"
#25000
bx +
bx /
bx ?
1F
bx (
bx 8
bx >
bx H
b1010101010 '
b1010101010 B
b1 E
b1 A
b1 3
b100001 &
b100001 J
b10 %
b10 4
b10 I
b10 6
b11 5
1"
#30000
0"
#35000
0)
b100 5
1"
#40000
0"
#45000
b101 5
1"
#50000
0"
#55000
1;
b10 (
b10 8
b10 >
b10 H
0<
b1001 =
0F
b10010010 C
b110010010 '
b110010010 B
b10 E
b10 A
b10 3
b1100010 &
b1100010 J
bx *
bx 9
bx L
b11 %
b11 4
b11 I
b11 6
1)
b110 5
1"
#60000
0"
#65000
0;
b0 +
b0 /
b0 ?
1<
b1010 =
b0 (
b0 8
b0 >
b0 H
b10101010 '
b10101010 B
b10101010 C
b0 E
b0 A
b0 3
b11000000 &
b11000000 J
b100 %
b100 4
b100 I
b100 6
b111 5
1"
#70000
0"
#75000
0)
b1000 5
1"
#80000
0"
#85000
b1001 5
1"
#90000
0"
#95000
b1111 +
b1111 /
b1111 ?
b1100 =
12
1F
bx (
bx 8
bx >
bx H
b11001111 C
b1011001111 '
b1011001111 B
b1111 E
b1111 A
b1111 3
b11111111 &
b11111111 J
b0 *
b0 9
b0 L
b0 !
b0 #
b0 ,
b0 0
b0 :
b0 M
b101 %
b101 4
b101 I
b101 6
1)
b1010 5
1"
#100000
0"
#105000
b110 %
b110 4
b110 I
b110 6
b1011 5
1"
#110000
0"
#115000
0)
b1100 5
1"
#120000
0"
#125000
b1101 5
1"
#130000
0"
#135000
b1111 !
b1111 #
b1111 ,
b1111 0
b1111 :
b1111 M
bx *
bx 9
bx L
b111 %
b111 4
b111 I
b111 6
1)
b1110 5
1"
#140000
0"
#145000
b1000 %
b1000 4
b1000 I
b1000 6
b1111 5
1"
#150000
0"
#155000
0)
b10000 5
1"
#160000
0"
#165000
b10001 5
1"
#170000
0"
#175000
b1001 %
b1001 4
b1001 I
b1001 6
1)
b10010 5
1"
#180000
0"
#185000
b1010 %
b1010 4
b1010 I
b1010 6
b10011 5
1"
#190000
0"
#195000
0)
b10100 5
1"
#200000
0"
#205000
b10101 5
1"
#210000
0"
#215000
b1011 %
b1011 4
b1011 I
b1011 6
1)
b10110 5
1"
#220000
0"
#225000
b1100 %
b1100 4
b1100 I
b1100 6
b10111 5
1"
#230000
0"
#235000
0)
b11000 5
1"
#240000
0"
#245000
b11001 5
1"
#250000
0"
#255000
b1101 %
b1101 4
b1101 I
b1101 6
1)
b11010 5
1"
#260000
0"
#265000
b1110 %
b1110 4
b1110 I
b1110 6
b11011 5
1"
#270000
0"
#275000
0)
b11100 5
1"
#280000
0"
#285000
b11101 5
1"
#290000
0"
#295000
b1111 %
b1111 4
b1111 I
b1111 6
1)
b11110 5
1"
#300000
0"
#305000
0-
1;
b1 +
b1 /
b1 ?
b1 @
b10 (
b10 8
b10 >
b10 H
0<
b1001 =
02
0F
b10010010 C
b110010010 '
b110010010 B
b10 E
b10 A
b10 3
b10000010 &
b10000010 J
b0 %
b0 4
b0 I
b0 6
b11111 5
1"
#310000
0"
#315000
0)
b100000 5
1"
#320000
0"
#325000
b100001 5
1"
#330000
0"
#335000
0;
1<
b1010 =
b0 (
b0 8
b0 >
b0 H
b10101010 '
b10101010 B
b10101010 C
b0 E
b0 A
b0 3
b0 +
b0 /
b0 ?
b11 @
b10000 &
b10000 J
b10 *
b10 9
b10 L
b1 !
b1 #
b1 ,
b1 0
b1 :
b1 M
b1 %
b1 4
b1 I
b1 6
1)
b100010 5
1"
#340000
0"
#345000
bx +
bx /
bx ?
1F
bx (
bx 8
bx >
bx H
b1010101010 '
b1010101010 B
b1 E
b1 A
b1 3
b100001 &
b100001 J
b10 %
b10 4
b10 I
b10 6
b100011 5
1"
#350000
0"
#355000
0)
b100100 5
1"
#360000
0"
#365000
b100101 5
1"
#370000
0"
#375000
x-
1;
bx @
b10 (
b10 8
b10 >
b10 H
0<
b1001 =
0F
b10010010 C
b110010010 '
b110010010 B
b10 E
b10 A
b10 3
b1100010 &
b1100010 J
bx !
bx #
bx ,
bx 0
bx :
bx M
bx *
bx 9
bx L
b11 %
b11 4
b11 I
b11 6
1)
b100110 5
1"
#380000
0"
#385000
0;
b0 +
b0 /
b0 ?
1<
b1010 =
b0 (
b0 8
b0 >
b0 H
b10101010 '
b10101010 B
b10101010 C
b0 E
b0 A
b0 3
b11000000 &
b11000000 J
b100 %
b100 4
b100 I
b100 6
b100111 5
1"
#390000
0"
#395000
0)
b101000 5
1"
#400000
0"
#405000
b101001 5
1"
#410000
0"
#415000
b1111 +
b1111 /
b1111 ?
b1100 =
12
1F
bx (
bx 8
bx >
bx H
b11001111 C
b1011001111 '
b1011001111 B
b1111 E
b1111 A
b1111 3
b11111111 &
b11111111 J
b0 *
b0 9
b0 L
b0 !
b0 #
b0 ,
b0 0
b0 :
b0 M
b101 %
b101 4
b101 I
b101 6
1)
b101010 5
1"
#420000
0"
#425000
b110 %
b110 4
b110 I
b110 6
b101011 5
1"
#430000
0"
#435000
0)
b101100 5
1"
#440000
0"
#445000
b101101 5
1"
#450000
0"
#455000
b1111 !
b1111 #
b1111 ,
b1111 0
b1111 :
b1111 M
bx *
bx 9
bx L
b111 %
b111 4
b111 I
b111 6
1)
b101110 5
1"
#460000
0"
#465000
b1000 %
b1000 4
b1000 I
b1000 6
b101111 5
1"
#470000
0"
#475000
0)
b110000 5
1"
#480000
0"
#485000
b110001 5
1"
#490000
0"
#495000
b1001 %
b1001 4
b1001 I
b1001 6
1)
b110010 5
1"
#500000
0"
#505000
b1010 %
b1010 4
b1010 I
b1010 6
b110011 5
1"
#510000
0"
#515000
0)
b110100 5
1"
#520000
0"
#525000
b110101 5
1"
#530000
0"
#535000
b1011 %
b1011 4
b1011 I
b1011 6
1)
b110110 5
1"
#540000
0"
#545000
b1100 %
b1100 4
b1100 I
b1100 6
b110111 5
1"
#550000
0"
#555000
0)
b111000 5
1"
#560000
0"
#565000
b111001 5
1"
#570000
0"
#575000
b1101 %
b1101 4
b1101 I
b1101 6
1)
b111010 5
1"
#580000
0"
#585000
b1110 %
b1110 4
b1110 I
b1110 6
b111011 5
1"
#590000
0"
#595000
0)
b111100 5
1"
#600000
0"
#605000
b111101 5
1"
#610000
0"
#615000
b1111 %
b1111 4
b1111 I
b1111 6
1)
b111110 5
1"
#620000
0"
#625000
0-
1;
b1 +
b1 /
b1 ?
b1 @
b10 (
b10 8
b10 >
b10 H
0<
b1001 =
02
0F
b10010010 C
b110010010 '
b110010010 B
b10 E
b10 A
b10 3
b10000010 &
b10000010 J
b0 %
b0 4
b0 I
b0 6
b111111 5
1"
#630000
0"
#635000
0)
b1000000 5
1"
#640000
0"
#645000
b1000001 5
1"
#650000
0"
#655000
0;
1<
b1010 =
b0 (
b0 8
b0 >
b0 H
b10101010 '
b10101010 B
b10101010 C
b0 E
b0 A
b0 3
b0 +
b0 /
b0 ?
b11 @
b10000 &
b10000 J
b10 *
b10 9
b10 L
b1 !
b1 #
b1 ,
b1 0
b1 :
b1 M
b1 %
b1 4
b1 I
b1 6
1)
b1000010 5
1"
#660000
0"
#665000
bx +
bx /
bx ?
1F
bx (
bx 8
bx >
bx H
b1010101010 '
b1010101010 B
b1 E
b1 A
b1 3
b100001 &
b100001 J
b10 %
b10 4
b10 I
b10 6
b1000011 5
1"
#670000
0"
#675000
0)
b1000100 5
1"
#680000
0"
#685000
b1000101 5
1"
#690000
0"
#695000
x-
1;
bx @
b10 (
b10 8
b10 >
b10 H
0<
b1001 =
0F
b10010010 C
b110010010 '
b110010010 B
b10 E
b10 A
b10 3
b1100010 &
b1100010 J
bx !
bx #
bx ,
bx 0
bx :
bx M
bx *
bx 9
bx L
b11 %
b11 4
b11 I
b11 6
1)
b1000110 5
1"
#700000
0"
#705000
0;
b0 +
b0 /
b0 ?
1<
b1010 =
b0 (
b0 8
b0 >
b0 H
b10101010 '
b10101010 B
b10101010 C
b0 E
b0 A
b0 3
b11000000 &
b11000000 J
b100 %
b100 4
b100 I
b100 6
b1000111 5
1"
#710000
0"
#715000
0)
b1001000 5
1"
#720000
0"
#725000
b1001001 5
1"
#730000
0"
#735000
b1111 +
b1111 /
b1111 ?
b1100 =
12
1F
bx (
bx 8
bx >
bx H
b11001111 C
b1011001111 '
b1011001111 B
b1111 E
b1111 A
b1111 3
b11111111 &
b11111111 J
b0 *
b0 9
b0 L
b0 !
b0 #
b0 ,
b0 0
b0 :
b0 M
b101 %
b101 4
b101 I
b101 6
1)
b1001010 5
1"
#740000
0"
#745000
b110 %
b110 4
b110 I
b110 6
b1001011 5
1"
#750000
0"
#755000
0)
b1001100 5
1"
#760000
0"
#765000
b1001101 5
1"
#770000
0"
#775000
b1111 !
b1111 #
b1111 ,
b1111 0
b1111 :
b1111 M
bx *
bx 9
bx L
b111 %
b111 4
b111 I
b111 6
1)
b1001110 5
1"
#780000
0"
#785000
b1000 %
b1000 4
b1000 I
b1000 6
b1001111 5
1"
#790000
0"
#795000
0)
b1010000 5
1"
#800000
0"
#805000
b1010001 5
1"
#810000
0"
#815000
b1001 %
b1001 4
b1001 I
b1001 6
1)
b1010010 5
1"
#820000
0"
#825000
b1010 %
b1010 4
b1010 I
b1010 6
b1010011 5
1"
#830000
0"
#835000
0)
b1010100 5
1"
#840000
0"
#845000
b1010101 5
1"
#850000
0"
#855000
b1011 %
b1011 4
b1011 I
b1011 6
1)
b1010110 5
1"
#860000
0"
#865000
b1100 %
b1100 4
b1100 I
b1100 6
b1010111 5
1"
#870000
0"
#875000
0)
b1011000 5
1"
#880000
0"
#885000
b1011001 5
1"
#890000
0"
#895000
b1101 %
b1101 4
b1101 I
b1101 6
1)
b1011010 5
1"
#900000
0"
#905000
b1110 %
b1110 4
b1110 I
b1110 6
b1011011 5
1"
#910000
0"
#915000
0)
b1011100 5
1"
#920000
0"
#925000
b1011101 5
1"
#930000
0"
#935000
b1111 %
b1111 4
b1111 I
b1111 6
1)
b1011110 5
1"
#940000
0"
#945000
0-
1;
b1 +
b1 /
b1 ?
b1 @
b10 (
b10 8
b10 >
b10 H
0<
b1001 =
02
0F
b10010010 C
b110010010 '
b110010010 B
b10 E
b10 A
b10 3
b10000010 &
b10000010 J
b0 %
b0 4
b0 I
b0 6
b1011111 5
1"
#950000
0"
#955000
0)
b1100000 5
1"
#960000
0"
#965000
b1100001 5
1"
#970000
0"
#975000
0;
1<
b1010 =
b0 (
b0 8
b0 >
b0 H
b10101010 '
b10101010 B
b10101010 C
b0 E
b0 A
b0 3
b0 +
b0 /
b0 ?
b11 @
b10000 &
b10000 J
b10 *
b10 9
b10 L
b1 !
b1 #
b1 ,
b1 0
b1 :
b1 M
b1 %
b1 4
b1 I
b1 6
1)
b1100010 5
1"
#980000
0"
#985000
bx +
bx /
bx ?
1F
bx (
bx 8
bx >
bx H
b1010101010 '
b1010101010 B
b1 E
b1 A
b1 3
b100001 &
b100001 J
b10 %
b10 4
b10 I
b10 6
b1100011 5
1"
#990000
0"
#995000
0)
b1100100 5
1"
#1000000
0"
#1005000
b1100101 5
1"
#1010000
0"
#1015000
x-
1;
bx @
b10 (
b10 8
b10 >
b10 H
0<
b1001 =
0F
b10010010 C
b110010010 '
b110010010 B
b10 E
b10 A
b10 3
b1100010 &
b1100010 J
bx !
bx #
bx ,
bx 0
bx :
bx M
bx *
bx 9
bx L
b11 %
b11 4
b11 I
b11 6
1)
b1100110 5
1"
#1020000
0"
#1025000
0;
b0 +
b0 /
b0 ?
1<
b1010 =
b0 (
b0 8
b0 >
b0 H
b10101010 '
b10101010 B
b10101010 C
b0 E
b0 A
b0 3
b11000000 &
b11000000 J
b100 %
b100 4
b100 I
b100 6
b1100111 5
1"
#1030000
0"
#1035000
0)
b1101000 5
1"
#1040000
0"
#1045000
b1101001 5
1"
#1050000
0"
#1055000
b1111 +
b1111 /
b1111 ?
b1100 =
12
1F
bx (
bx 8
bx >
bx H
b11001111 C
b1011001111 '
b1011001111 B
b1111 E
b1111 A
b1111 3
b11111111 &
b11111111 J
b0 *
b0 9
b0 L
b0 !
b0 #
b0 ,
b0 0
b0 :
b0 M
b101 %
b101 4
b101 I
b101 6
1)
b1101010 5
1"
#1060000
0"
#1065000
b110 %
b110 4
b110 I
b110 6
b1101011 5
1"
#1070000
0"
#1075000
0)
b1101100 5
1"
#1080000
0"
#1085000
b1101101 5
1"
#1090000
0"
#1095000
b1111 !
b1111 #
b1111 ,
b1111 0
b1111 :
b1111 M
bx *
bx 9
bx L
b111 %
b111 4
b111 I
b111 6
1)
b1101110 5
1"
#1100000
0"
#1105000
b1000 %
b1000 4
b1000 I
b1000 6
b1101111 5
1"
#1110000
0"
#1115000
0)
b1110000 5
1"
#1120000
0"
#1125000
b1110001 5
1"
#1130000
0"
#1135000
b1001 %
b1001 4
b1001 I
b1001 6
1)
b1110010 5
1"
#1140000
0"
#1145000
b1010 %
b1010 4
b1010 I
b1010 6
b1110011 5
1"
#1150000
0"
#1155000
0)
b1110100 5
1"
#1160000
0"
#1165000
b1110101 5
1"
#1170000
0"
#1175000
b1011 %
b1011 4
b1011 I
b1011 6
1)
b1110110 5
1"
#1180000
0"
#1185000
b1100 %
b1100 4
b1100 I
b1100 6
b1110111 5
1"
#1190000
0"
#1195000
0)
b1111000 5
1"
#1200000
0"
#1205000
b1111001 5
1"
#1210000
0"
#1215000
b1101 %
b1101 4
b1101 I
b1101 6
1)
b1111010 5
1"
#1220000
0"
#1225000
b1110 %
b1110 4
b1110 I
b1110 6
b1111011 5
1"
#1230000
0"
#1235000
0)
b1111100 5
1"
#1240000
0"
#1245000
b1111101 5
1"
#1250000
0"
#1255000
b1111 %
b1111 4
b1111 I
b1111 6
1)
b1111110 5
1"
#1260000
0"
#1265000
0-
1;
b1 +
b1 /
b1 ?
b1 @
b10 (
b10 8
b10 >
b10 H
0<
b1001 =
02
0F
b10010010 C
b110010010 '
b110010010 B
b10 E
b10 A
b10 3
b10000010 &
b10000010 J
b0 %
b0 4
b0 I
b0 6
b1111111 5
1"
#1270000
0"
#1275000
0)
b10000000 5
1"
#1280000
0"
#1285000
b10000001 5
1"
#1290000
0"
#1295000
0;
1<
b1010 =
b0 (
b0 8
b0 >
b0 H
b10101010 '
b10101010 B
b10101010 C
b0 E
b0 A
b0 3
b0 +
b0 /
b0 ?
b11 @
b10000 &
b10000 J
b10 *
b10 9
b10 L
b1 !
b1 #
b1 ,
b1 0
b1 :
b1 M
b1 %
b1 4
b1 I
b1 6
1)
b10000010 5
1"
#1300000
0"
#1305000
bx +
bx /
bx ?
1F
bx (
bx 8
bx >
bx H
b1010101010 '
b1010101010 B
b1 E
b1 A
b1 3
b100001 &
b100001 J
b10 %
b10 4
b10 I
b10 6
b10000011 5
1"
#1310000
0"
#1315000
0)
b10000100 5
1"
#1320000
0"
#1325000
b10000101 5
1"
#1330000
0"
#1335000
x-
1;
bx @
b10 (
b10 8
b10 >
b10 H
0<
b1001 =
0F
b10010010 C
b110010010 '
b110010010 B
b10 E
b10 A
b10 3
b1100010 &
b1100010 J
bx !
bx #
bx ,
bx 0
bx :
bx M
bx *
bx 9
bx L
b11 %
b11 4
b11 I
b11 6
1)
b10000110 5
1"
#1340000
0"
#1345000
0;
b0 +
b0 /
b0 ?
1<
b1010 =
b0 (
b0 8
b0 >
b0 H
b10101010 '
b10101010 B
b10101010 C
b0 E
b0 A
b0 3
b11000000 &
b11000000 J
b100 %
b100 4
b100 I
b100 6
b10000111 5
1"
#1350000
0"
#1355000
0)
b10001000 5
1"
#1360000
0"
#1365000
b10001001 5
1"
#1370000
0"
#1375000
b1111 +
b1111 /
b1111 ?
b1100 =
12
1F
bx (
bx 8
bx >
bx H
b11001111 C
b1011001111 '
b1011001111 B
b1111 E
b1111 A
b1111 3
b11111111 &
b11111111 J
b0 *
b0 9
b0 L
b0 !
b0 #
b0 ,
b0 0
b0 :
b0 M
b101 %
b101 4
b101 I
b101 6
1)
b10001010 5
1"
#1380000
0"
#1385000
b110 %
b110 4
b110 I
b110 6
b10001011 5
1"
#1390000
0"
#1395000
0)
b10001100 5
1"
#1400000
0"
#1405000
b10001101 5
1"
#1410000
0"
#1415000
b1111 !
b1111 #
b1111 ,
b1111 0
b1111 :
b1111 M
bx *
bx 9
bx L
b111 %
b111 4
b111 I
b111 6
1)
b10001110 5
1"
#1420000
0"
#1425000
b1000 %
b1000 4
b1000 I
b1000 6
b10001111 5
1"
#1430000
0"
#1435000
0)
b10010000 5
1"
#1440000
0"
#1445000
b10010001 5
1"
#1450000
0"
#1455000
b1001 %
b1001 4
b1001 I
b1001 6
1)
b10010010 5
1"
#1460000
0"
#1465000
b1010 %
b1010 4
b1010 I
b1010 6
b10010011 5
1"
#1470000
0"
#1475000
0)
b10010100 5
1"
#1480000
0"
#1485000
b10010101 5
1"
#1490000
0"
#1495000
b1011 %
b1011 4
b1011 I
b1011 6
1)
b10010110 5
1"
#1500000
0"
#1505000
b1100 %
b1100 4
b1100 I
b1100 6
b10010111 5
1"
#1510000
0"
#1515000
0)
b10011000 5
1"
#1520000
0"
#1525000
b10011001 5
1"
#1530000
0"
#1535000
b1101 %
b1101 4
b1101 I
b1101 6
1)
b10011010 5
1"
#1540000
0"
#1545000
b1110 %
b1110 4
b1110 I
b1110 6
b10011011 5
1"
#1550000
0"
#1555000
0)
b10011100 5
1"
#1560000
0"
#1565000
b10011101 5
1"
#1570000
0"
#1575000
b1111 %
b1111 4
b1111 I
b1111 6
1)
b10011110 5
1"
#1580000
0"
#1585000
0-
1;
b1 +
b1 /
b1 ?
b1 @
b10 (
b10 8
b10 >
b10 H
0<
b1001 =
02
0F
b10010010 C
b110010010 '
b110010010 B
b10 E
b10 A
b10 3
b10000010 &
b10000010 J
b0 %
b0 4
b0 I
b0 6
b10011111 5
1"
#1590000
0"
#1595000
0)
b10100000 5
1"
#1600000
0"
#1605000
b10100001 5
1"
#1610000
0"
#1615000
0;
1<
b1010 =
b0 (
b0 8
b0 >
b0 H
b10101010 '
b10101010 B
b10101010 C
b0 E
b0 A
b0 3
b0 +
b0 /
b0 ?
b11 @
b10000 &
b10000 J
b10 *
b10 9
b10 L
b1 !
b1 #
b1 ,
b1 0
b1 :
b1 M
b1 %
b1 4
b1 I
b1 6
1)
b10100010 5
1"
#1620000
0"
#1625000
bx +
bx /
bx ?
1F
bx (
bx 8
bx >
bx H
b1010101010 '
b1010101010 B
b1 E
b1 A
b1 3
b100001 &
b100001 J
b10 %
b10 4
b10 I
b10 6
b10100011 5
1"
#1630000
0"
#1635000
0)
b10100100 5
1"
#1640000
0"
#1645000
b10100101 5
1"
#1650000
0"
#1655000
x-
1;
bx @
b10 (
b10 8
b10 >
b10 H
0<
b1001 =
0F
b10010010 C
b110010010 '
b110010010 B
b10 E
b10 A
b10 3
b1100010 &
b1100010 J
bx !
bx #
bx ,
bx 0
bx :
bx M
bx *
bx 9
bx L
b11 %
b11 4
b11 I
b11 6
1)
b10100110 5
1"
#1660000
0"
#1665000
0;
b0 +
b0 /
b0 ?
1<
b1010 =
b0 (
b0 8
b0 >
b0 H
b10101010 '
b10101010 B
b10101010 C
b0 E
b0 A
b0 3
b11000000 &
b11000000 J
b100 %
b100 4
b100 I
b100 6
b10100111 5
1"
#1670000
0"
#1675000
0)
b10101000 5
1"
#1680000
0"
#1685000
b10101001 5
1"
#1690000
0"
#1695000
b1111 +
b1111 /
b1111 ?
b1100 =
12
1F
bx (
bx 8
bx >
bx H
b11001111 C
b1011001111 '
b1011001111 B
b1111 E
b1111 A
b1111 3
b11111111 &
b11111111 J
b0 *
b0 9
b0 L
b0 !
b0 #
b0 ,
b0 0
b0 :
b0 M
b101 %
b101 4
b101 I
b101 6
1)
b10101010 5
1"
#1700000
0"
#1705000
b110 %
b110 4
b110 I
b110 6
b10101011 5
1"
#1710000
0"
#1715000
0)
b10101100 5
1"
#1720000
0"
#1725000
b10101101 5
1"
#1730000
0"
#1735000
b1111 !
b1111 #
b1111 ,
b1111 0
b1111 :
b1111 M
bx *
bx 9
bx L
b111 %
b111 4
b111 I
b111 6
1)
b10101110 5
1"
#1740000
0"
#1745000
b1000 %
b1000 4
b1000 I
b1000 6
b10101111 5
1"
#1750000
0"
#1755000
0)
b10110000 5
1"
#1760000
0"
#1765000
b10110001 5
1"
#1770000
0"
#1775000
b1001 %
b1001 4
b1001 I
b1001 6
1)
b10110010 5
1"
#1780000
0"
